Workbook

Sheet 00_Synthese
A1: Tantalus Frontier — V162
A2: 00_Synthese
A3: Prépublication : implémentation et validation du commit restent distinctes.
A5: Indicateur | E5: Compte vérifiable
A7: Identités du roster conservées | E7: =COUNTA('08_Roster'!A6:A194) -> 189
A8: Rigs natifs concernés | E8: =SUM('08_Roster'!D6:D194) -> 4
A9: Séquences techniques cumulées | E9: =COUNTA('03_Sequences'!A6:A45) -> 40
A10: Points clés explicitement écrits | E10: =SUM('03_Sequences'!E6:E45) -> 200
A11: Présentations V146 conservées | E11: =COUNTA('01_Presentations'!A6:A45) -> 40
A12: Présentations techniquement raccordées | E12: =COUNTA('01_Presentations'!E6:E45) -> 40
A13: Tâches ART153 conservées | E13: =COUNTA('02_ART153'!A6:A33) -> 28
A14: Annexes avec affectation conditionnelle | E14: =COUNTIF('04_Annexes'!G6:G24,"Affectation technique conditionnelle") -> 19
A15: Contrats narratifs Forge suivis | E15: =COUNTA('05_Forge'!A6:A17) -> 12
A16: Clôtures artistiques complètes | E16: =SUM('01_Presentations'!G6:G45) -> 0
A17: Présentations approuvées 1:1 | E17: =SUM('01_Presentations'!H6:H45) -> 0
A18: Accès d’opérations actifs déjà jouables | E18: =SUM('10_Operations'!E6:E26) -> 21
A19: Rigs avec sortie spatiale bornée | E19: =COUNTA('12_TrialsSortie'!A6:A9) -> 4
A20: Identités avec registre de preuve distinct | E20: =COUNTA('13_Preuve1to1'!A6:A194) -> 189
A21: Identités certifiées 1:1 à l’œuvre | E21: =SUM('13_Preuve1to1'!K6:K194) -> 0
A22: Lots techniques V159 suivis | E22: =COUNTA('15_LotsV159'!A6:A6) -> 1
A23: Réceptions natives adaptées | E23: =COUNTIF('02_ART153'!E6:E33,"Implémenté (adaptation native)") -> 3
A24: Chantiers utilisateur V160 distincts des 68 tâches Trials | E24: =COUNTA('18_ChantiersV160'!A6:A9) -> 4
A25: Clôtures artistiques des quatre chantiers V160 | E25: =SUM('18_ChantiersV160'!L6:L9) -> 0
A26: Chantiers V160 certifiés 1:1 | E26: =SUM('18_ChantiersV160'!M6:M9) -> 0
A27: Manquants repris V161 distincts des 68 tâches Trials | E27: =COUNTA('21_ChantiersV161'!A6:A8) -> 3
A28: Clôtures artistiques V161 | E28: =SUM('21_ChantiersV161'!I6:I8) -> 0
A29: Certifications 1:1 V161 | E29: =SUM('21_ChantiersV161'!J6:J8) -> 0
A30: Périmètres hors Forge V162 distincts des 68 tâches Trials | E30: =COUNTA('22_ChantiersV162'!A6:A9) -> 4
A31: Clôtures artistiques V162 | E31: =SUM('22_ChantiersV162'!I6:I9) -> 0
A32: Certifications 1:1 V162 | E32: =SUM('22_ChantiersV162'!J6:J9) -> 0

Sheet 01_Presentations
A1: Tantalus Frontier — V162
A2: 01_Presentations
A3: Prépublication : implémentation et validation du commit restent distinctes.
A5: Présentation V146 | B5: Identité | C5: Séquence prévue | D5: État | E5: Implémentation V155 | F5: Livré / manquant | G5: Clos artistiquement | H5: Approuvé 1:1
A6: prowler::intro | B6: Prowler | C6: Intro standard | D6: Partiel | E6: prowler::intro | F6: Entrée V155 conservée sur le rig natif. Adaptation de simulation ; dessins complets, audio et relevés d’œuvre restent ouverts. Aucun lot artistique clos ni certification 1:1. | G6: 0 | H6: 0
A7: prowler::intro-rival | B7: Prowler | C7: Intro de rivalité | D7: Partiel | E7: prowler::intro-rival | F7: Réponse à la famille effective de l’adversaire, y compris hybride, pendant sa présentation ; aucune rivalité historique affirmée. Adaptation de simulation ; dessins complets, audio et relevés d’œuvre restent ouverts. Aucun lot artistique clos ni certification 1:1. | G7: 0 | H7: 0
A8: prowler::outro | B8: Prowler | C8: Outro | D8: Partiel | E8: prowler::outro | F8: V157 ajoute une retombée de rendu bornée si le verdict fige le rig en l’air, puis une sortie vers les bords. Corps physiques et verdict inchangés ; phases historiques au sol intactes. Dessins, audio et revue 1:1 restent ouverts. | G8: 0 | H8: 0
A9: prowler::win-r1 | B9: Prowler | C9: Victoire de première manche | D9: Partiel | E9: prowler::round-win | F9: Réaction V155 réversible de victoire de manche conservée. Adaptation de simulation ; dessins complets, audio et relevés d’œuvre restent ouverts. Aucun lot artistique clos ni certification 1:1. | G9: 0 | H9: 0
A10: prowler::lose-r1 | B10: Prowler | C10: Défaite de première manche | D10: Partiel | E10: prowler::round-loss | F10: Récupération V155 réversible de défaite de manche conservée. Adaptation de simulation ; dessins complets, audio et relevés d’œuvre restent ouverts. Aucun lot artistique clos ni certification 1:1. | G10: 0 | H10: 0
A11: prowler::win-final | B11: Prowler | C11: Victoire finale | D11: Partiel | E11: prowler::outro-win | F11: Pose V155 de victoire terminale conservée ; aucun second résultat ni paiement. Adaptation de simulation ; dessins complets, audio et relevés d’œuvre restent ouverts. Aucun lot artistique clos ni certification 1:1. | G11: 0 | H11: 0
A12: prowler::lose-final | B12: Prowler | C12: Défaite finale | D12: Partiel | E12: prowler::outro-loss | F12: Pose V155 de défaite terminale conservée ; ce n’est pas une chute complète. Adaptation de simulation ; dessins complets, audio et relevés d’œuvre restent ouverts. Aucun lot artistique clos ni certification 1:1. | G12: 0 | H12: 0
A13: prowler::draw | B13: Prowler | C13: Égalité | D13: Partiel | E13: prowler::draw | F13: Réaction sans vainqueur sur égalité réelle de manche ou de match ; ne force aucun résultat. Adaptation de simulation ; dessins complets, audio et relevés d’œuvre restent ouverts. Aucun lot artistique clos ni certification 1:1. | G13: 0 | H13: 0
A14: prowler::taunt | B14: Prowler | C14: Provocation | D14: Partiel | E14: prowler::taunt | F14: Commande T ou bouton DÉFI pendant le combat ; le bouton rend le focus au canvas quand le combat accepte les commandes. Annulation par déplacement, attaque, garde ou impact. Adaptation de simulation ; dessins complets, audio et relevés d’œuvre restent ouverts. Aucun lot artistique clos ni certification 1:1. | G14: 0 | H14: 0
A15: prowler::rematch | B15: Prowler | C15: Début de manche suivante | D15: Partiel | E15: prowler::rematch | F15: Reprise visuelle pendant le décompte existant des manches suivantes, sans nouvel équipement ni changement physique. Adaptation de simulation ; dessins complets, audio et relevés d’œuvre restent ouverts. Aucun lot artistique clos ni certification 1:1. | G15: 0 | H15: 0
A16: import-game-dd-wy-commando::intro | B16: Weyland-Yutani Commando — Altered — adaptation | C16: Intro standard | D16: Partiel | E16: import-game-dd-wy-commando::intro | F16: Entrée V155 conservée sur le rig natif. Adaptation de simulation ; dessins complets, audio et relevés d’œuvre restent ouverts. Aucun lot artistique clos ni certification 1:1. | G16: 0 | H16: 0
A17: import-game-dd-wy-commando::intro-rival | B17: Weyland-Yutani Commando — Altered — adaptation | C17: Intro de rivalité | D17: Partiel | E17: import-game-dd-wy-commando::intro-rival | F17: Réponse à la famille effective de l’adversaire, y compris hybride, pendant sa présentation ; aucune rivalité historique affirmée. Adaptation de simulation ; dessins complets, audio et relevés d’œuvre restent ouverts. Aucun lot artistique clos ni certification 1:1. | G17: 0 | H17: 0
... A45: dd-darwin-era-cultist::rematch | B45: Cultiste Darwin Era | C45: Début de manche suivante | D45: Partiel | E45: dd-darwin-era-cultist::rematch | F45: Reprise visuelle pendant le décompte existant des manches suivantes, sans nouvel équipement ni changement physique. Adaptation de simulation ; dessins complets, audio et relevés d’œuvre restent ouverts. Aucun lot artistique clos ni certification 1:1. | G45: 0 | H45: 0

Sheet 02_ART153
A1: Tantalus Frontier — V162
A2: 02_ART153
A3: Prépublication : implémentation et validation du commit restent distinctes.
A5: Tâche héritée | B5: Identité | C5: ID exact | D5: Travail | E5: État | F5: Livré / reste à produire | G5: Lot | H5: Approuvé 1:1
A6: ART153-01 | B6: Prowler | C6: prowler | D6: Références de poses et timecodes | E6: À relever | F6: Coordonnées mesurées sur le sprite du projet ; référence d’œuvre et timecodes non relevés. | G6: V154 | H6: 0
A7: ART153-02 | B7: Prowler | C7: prowler | D7: Rig et points de contact | E7: Implémenté (adaptation) | F7: Rig exact, maillage, points de contact et appuis ; source native inchangée. Validation canonique non acquise. | G7: V154 | H7: 0
A8: ART153-03 | B8: Prowler | C8: prowler | D8: Préparation / capture | E8: Partiel | F8: Anticipation du bond adaptée. | G8: V154 | H8: 0
A9: ART153-04 | B9: Prowler | C9: prowler | D9: Saisie articulée | E9: Partiel | F9: Réaction de corps debout ; mise au sol et raccords entre les deux corps à produire. | G9: V154 | H9: 0
A10: ART153-05 | B10: Prowler | C10: prowler | D10: Résistance / dégagement | E10: Partiel | F10: Réaction au progrès réel du dégagement ; chorégraphie complète à produire. | G10: V154 | H10: 0
A11: ART153-06 | B11: Prowler | C11: prowler | D11: Interruption / récupération | E11: Implémenté (adaptation) | F11: Récupération courte déclenchée par la libération réelle, sans rejouer une attaque. | G11: V154 | H11: 0
A12: ART153-07 | B12: Prowler | C12: prowler | D12: Revue deux orientations et tailles | E12: À valider | F12: Mathématiques et deux orientations couvertes par tests ; validation artistique finale et 1:1 encore ouverte. | G12: V154 | H12: 0
A13: ART153-08 | B13: Weyland-Yutani Commando — Altered — adaptation | C13: import-game-dd-wy-commando | D13: Références de poses et timecodes | E13: À relever | F13: Coordonnées mesurées sur le sprite du projet ; référence d’œuvre et timecodes non relevés. | G13: V154 | H13: 0
A14: ART153-09 | B14: Weyland-Yutani Commando — Altered — adaptation | C14: import-game-dd-wy-commando | D14: Rig et points de contact | E14: Implémenté (adaptation) | F14: Rig exact, maillage, points de contact et appuis ; source native inchangée. Validation canonique non acquise. | G14: V154 | H14: 0
A15: ART153-10 | B15: Weyland-Yutani Commando — Altered — adaptation | C15: import-game-dd-wy-commando | D15: Préparation / capture | E15: Implémenté (adaptation native) | F15: Réception bornée sur la plaque native exacte ; absorption puis raccord à la prise existante. Chorégraphie de simulation, sans mise au sol complète, pin ou référence de mouvement canonique. | G15: V158 | H15: 0
A16: ART153-11 | B16: Weyland-Yutani Commando — Altered — adaptation | C16: import-game-dd-wy-commando | D16: Saisie articulée | E16: Partiel | F16: Abaissement articulé borné sur la cible native, pieds et semelles fixes, cage des deux jambes ; ni corps couché ni pin complet. Dessins, mise au sol et raccords complets restent ouverts. | G16: V156 | H16: 0
A17: ART153-12 | B17: Weyland-Yutani Commando — Altered — adaptation | C17: import-game-dd-wy-commando | D17: Résistance / dégagement | E17: Partiel | F17: La résistance conserve l’abaissement de la cible et répond au progrès réel du dégagement. Chorégraphie de corps complète et validation artistique encore ouvertes. | G17: V156 | H17: 0
... A33: ART153-28 | B33: Cultiste Darwin Era | C33: dd-darwin-era-cultist | D33: Revue deux orientations et tailles | E33: À valider | F33: Supports, maillage et abaissement contrôlés dans les deux orientations par les tests techniques. Revue artistique finale et relevés 1:1 toujours ouverts. | G33: V156 | H33: 0

Sheet 03_Sequences
A1: Tantalus Frontier — V162
A2: 03_Sequences
A3: Prépublication : implémentation et validation du commit restent distinctes.
A5: Séquence_ID | B5: Identité | C5: Phase | D5: Durée (ms) | E5: Points clés | F5: Présentation V146 | G5: État technique | H5: Fidélité
A6: prowler::intro | B6: Prowler | C6: intro | D6: 1200 | E6: 5 | F6: prowler::intro | G6: Adaptation technique raccordée | H6: Non approuvé 1:1
A7: prowler::round-win | B7: Prowler | C7: round-win | D7: 1800 | E7: 5 | F7: prowler::win-r1 | G7: Adaptation technique raccordée | H7: Non approuvé 1:1
A8: prowler::round-loss | B8: Prowler | C8: round-loss | D8: 1800 | E8: 5 | F8: prowler::lose-r1 | G8: Adaptation technique raccordée | H8: Non approuvé 1:1
A9: prowler::outro-win | B9: Prowler | C9: outro-win | D9: 1800 | E9: 5 | F9: prowler::win-final | G9: Adaptation technique raccordée | H9: Non approuvé 1:1
A10: prowler::outro-loss | B10: Prowler | C10: outro-loss | D10: 1800 | E10: 5 | F10: prowler::lose-final | G10: Adaptation technique raccordée | H10: Non approuvé 1:1
A11: dd-darwin-era-cultist::intro | B11: Cultiste Darwin Era | C11: intro | D11: 1200 | E11: 5 | F11: dd-darwin-era-cultist::intro | G11: Adaptation technique raccordée | H11: Non approuvé 1:1
A12: dd-darwin-era-cultist::round-win | B12: Cultiste Darwin Era | C12: round-win | D12: 1800 | E12: 5 | F12: dd-darwin-era-cultist::win-r1 | G12: Adaptation technique raccordée | H12: Non approuvé 1:1
A13: dd-darwin-era-cultist::round-loss | B13: Cultiste Darwin Era | C13: round-loss | D13: 1800 | E13: 5 | F13: dd-darwin-era-cultist::lose-r1 | G13: Adaptation technique raccordée | H13: Non approuvé 1:1
A14: dd-darwin-era-cultist::outro-win | B14: Cultiste Darwin Era | C14: outro-win | D14: 1800 | E14: 5 | F14: dd-darwin-era-cultist::win-final | G14: Adaptation technique raccordée | H14: Non approuvé 1:1
A15: dd-darwin-era-cultist::outro-loss | B15: Cultiste Darwin Era | C15: outro-loss | D15: 1800 | E15: 5 | F15: dd-darwin-era-cultist::lose-final | G15: Adaptation technique raccordée | H15: Non approuvé 1:1
A16: import-game-dd-wy-commando::intro | B16: Weyland-Yutani Commando — Altered — adaptation | C16: intro | D16: 1200 | E16: 5 | F16: import-game-dd-wy-commando::intro | G16: Adaptation technique raccordée | H16: Non approuvé 1:1
A17: import-game-dd-wy-commando::round-win | B17: Weyland-Yutani Commando — Altered — adaptation | C17: round-win | D17: 1800 | E17: 5 | F17: import-game-dd-wy-commando::win-r1 | G17: Adaptation technique raccordée | H17: Non approuvé 1:1
... A45: import-game-dd-guardian::rematch | B45: Guardian — Darwin Era — adaptation | C45: rematch | D45: 3000 | E45: 5 | F45: import-game-dd-guardian::rematch | G45: Adaptation technique raccordée | H45: Non approuvé 1:1

Sheet 04_Annexes
A1: Tantalus Frontier — V162
A2: 04_Annexes
A3: Prépublication : implémentation et validation du commit restent distinctes.
A5: Annexe_ID | B5: Salle | C5: PNJ_ID | D5: Rôle | E5: Créneau déclaré | F5: Support | G5: État technique | H5: Portée / limites
A6: arrival-airlock | B6: Sas d’arrivée | C6: crew-08-maksim-orlov | D6: Sécurité des arrivées | E6: 10:30–12:00 | F6: Sol physique, y=624 | G6: Affectation technique conditionnelle | H6: Présence uniquement en phase de travail ; alertes, missions, repos et soins prioritaires. Rondes locales si rail≥70 px ; pas de trajet interannexes.
A7: logistics | B7: Soute / Logistique | C7: crew-16-cal-mercer | D7: Contrôle du fret | E7: 09:00–10:30 | F7: Passerelle physique logistique, y=468 | G7: Affectation technique conditionnelle | H7: Présence uniquement en phase de travail ; alertes, missions, repos et soins prioritaires. Rondes locales si rail≥70 px ; pas de trajet interannexes.
A8: mire-archives | B8: Archives MIRE / Palimpsest | C8: crew-01-mara-vega | D8: Revue des archives de commandement | E8: 10:30–12:00 | F8: Sol physique, y=624 | G8: Affectation technique conditionnelle | H8: Présence uniquement en phase de travail ; alertes, missions, repos et soins prioritaires. Rondes locales si rail≥70 px ; pas de trajet interannexes.
A9: synthetic-bay | B9: Baie synthétique | C9: crew-05-bishop-9 | D9: Diagnostic synthétique | E9: 09:00–10:30 | F9: Sol physique, y=624 | G9: Affectation technique conditionnelle | H9: Affectation native conditionnelle ; V159 suit le même BISHOP depuis science-lab par le sas apparié et le retour. Alerte : retrait réel prioritaire aux minuteurs, réservation dès le corps sur l’ouverture même à progression zéro, marche native pilotée par distance. Missions et soins prioritaires ; quarantaine et autres annexes hors de ce circuit.
A10: cctv | B10: Sécurité / CCTV | C10: crew-06-rook | D10: Revue de vidéosurveillance | E10: 09:00–10:30 | F10: Sol physique, y=624 | G10: Affectation technique conditionnelle | H10: Présence uniquement en phase de travail ; alertes, missions, repos et soins prioritaires. Rondes locales si rail≥70 px ; pas de trajet interannexes.
A11: proving-ground | B11: Proving Ground / Terrain d’essai | C11: crew-02-tamsin-velez | D11: Contrôle du terrain d’essai | E11: 09:00–10:30 | F11: Sol physique, y=624 | G11: Affectation technique conditionnelle | H11: Présence uniquement en phase de travail ; alertes, missions, repos et soins prioritaires. Rondes locales si rail≥70 px ; pas de trajet interannexes.
A12: morgue | B12: Morgue / Autopsie | C12: crew-04-noor-okafor, crew-09-inez-harlow | D12: Soins médico-légaux ; Identification des spécimens | E12: Quart V141 hors rotation ; Quart V141 hors rotation | F12: Sol physique, y=624 | G12: Affectation technique conditionnelle | H12: Présence uniquement en phase de travail ; alertes, missions, repos et soins prioritaires. Rondes locales si rail≥70 px ; pas de trajet interannexes.
A13: escape-pods | B13: Capsules de sauvetage | C13: crew-14-echo-a | D13: Préparation à l’évacuation | E13: 09:00–10:30 | F13: Sol physique, y=624 | G13: Affectation technique conditionnelle | H13: Présence uniquement en phase de travail ; alertes, missions, repos et soins prioritaires. Rondes locales si rail≥70 px ; pas de trajet interannexes.
A14: durandal | B14: Noyau DURANDAL Ω | C14: crew-10-david-8r | D14: Diagnostic informatique | E14: 10:30–12:00 | F14: Sol physique, y=624 | G14: Affectation technique conditionnelle | H14: Présence uniquement en phase de travail ; alertes, missions, repos et soins prioritaires. Rondes locales si rail≥70 px ; pas de trajet interannexes.
A15: bioforge | B15: Accès BIOFORGE isolé | C15: crew-09-inez-harlow | D15: Contrôle des spécimens isolés | E15: 10:30–12:00 | F15: Sol physique, y=624 | G15: Affectation technique conditionnelle | H15: Présence uniquement en phase de travail ; alertes, missions, repos et soins prioritaires. Rondes locales si rail≥70 px ; pas de trajet interannexes.
A16: animal-care | B16: Accueil des compagnons | C16: crew-04-noor-okafor | D16: Inspection du bien-être des compagnons | E16: 09:00–10:30 | F16: Sol physique étendu, y=624 | G16: Affectation technique conditionnelle | H16: Baie de service dégagée ; cycle de visite local et retour au poste. Couchages/enclos conservés ; mission, alerte, repos et soins prioritaires. Pas de trajet interannexes.
... A24: maintenance-spine | B24: Coursive technique traversante | C24: crew-11-jun-park, crew-13-pablo-reyes | D24: Ronde technique ; Contrôle d’isolement | E24: Quart V141 hors rotation ; Quart V141 hors rotation | F24: Sol physique, y=624 | G24: Affectation technique conditionnelle | H24: Présence uniquement en phase de travail ; alertes, missions, repos et soins prioritaires. Rondes locales si rail≥70 px ; pas de trajet interannexes.

Sheet 05_Forge
A1: Tantalus Frontier — V162
A2: 05_Forge
A3: Prépublication : implémentation et validation du commit restent distinctes.
A5: Contrat_ID | B5: Capacité | C5: Borne / condition | D5: État technique | E5: Limite
A6: forge-physical-terminal | B6: Récit sur terminal physique | C6: 64 terminaux par projet ; schema narratif 1 | D6: Implémenté (borné) | E6: Pas de récit sur un calque décoratif, pas de personnage parlant.
A7: forge-acyclic-graph | B7: Pages et réponses liées | C7: 1 à 8 nœuds par terminal ; au plus 2 choix ; graphe sans boucle | D7: Implémenté (borné) | E7: Les pages non liées restent des brouillons, pas une histoire parcourue.
A8: forge-text-limits | B8: Texte éditable | C8: Texte 600 caractères ; titre et réponse 100 | D8: Implémenté (borné) | E8: Textes affichés comme contenu, pas comme code ou balisage exécutable.
A9: forge-objective-condition | B9: Choix conditionné par objectif | C9: Objectif physique existant, y compris dans une autre salle | D9: Implémenté (borné) | E9: Objets de récit et seuil de temps actif V157 suivis séparément ; pas de condition arbitraire ni score libre.
A10: forge-objective-reward | B10: Validation d’un objectif par réponse | C10: Récompense d’objectif idempotente ; pas de boucle condition/récompense | D10: Implémenté (borné) | E10: Les objets de récit ne sont pas des objets de campagne ; aucun crédit ni script arbitraire.
A11: forge-inspector-versioning | B11: Édition, assemblages et versionnement | C11: Inspecteur, annuler/rétablir, JSON schema 3 et versions V136 ; capture, bibliothèque, rotation et pose préservent les références aux objectifs externes. | D11: Implémenté (borné) | E11: La validation du projet reste stricte. L’aperçu et la pose refusent les références absentes, décoratives ou en conflit physique.
A12: forge-native-choice | B12: Choix en playtest Mission / Vaisseau | C12: E choisit une action admissible ; admission commune aux actions et prompts natifs power/archive. Ordre power→archive après visibilité et verrou boss. Réanimation J2, clé et récupération restent déléguées au moteur natif. À la manette, admission avant les actions et arrêt du lot dès l’ouverture d’un récit, pour les deux joueurs. | D12: Implémenté (borné) | E12: Récupération seulement sans terminal en attente admis, sans objectif proche ni porte native cloisonnée ; profil, propriétaire, portée 72 et ligne de vue natifs conservés. Hors Forge : conditions historiques inchangées. Réarmement au neutre ; le refus direct du véhicule précède toute annulation de travail ou d’aperçu.
A13: forge-memory-session | B13: Curseur et historique entre salles | C13: Mémoire entre salles ; checkpoint local explicite séparé, lié au projet et à son équipement. | D13: Implémenté (borné) | E13: Pas de cloud Forge ni écriture des sauvegardes de campagne.
A14: forge-story-items-v157 | B14: Objets de récit nommés | C14: 32 objets uniques/projet ; 16 déclarations/terminal ; exiger, remettre ou consommer l’objet requis. | D14: Implémenté (borné) | E14: Pas d’arme, monnaie, inventaire de campagne ni script libre.
A15: forge-active-time-v157 | B15: Seuil de temps actif | C15: Entier 0–3 600 secondes ; simulation admise seulement, arrêt en pause et récit ouvert. | D15: Implémenté (borné) | E15: Pas d’horloge réelle hors jeu ni minuterie libre de campagne.
A16: forge-local-checkpoint-v157 | B16: Checkpoint local explicite | C16: Un slot ; 4 Mio ; même projet/équipe/équipement/véhicule de départ ; commandes visibles en 16:9/mobile ; focus sur le résumé avant désactivation, puis restauration gardée par moteur/session ; validation avant mutation. | D16: Implémenté (borné) | E16: Pas de cloud, de récompense automatique ni de copie des sauvegardes de campagne.
A17: forge-dialogue-npcs-v158 | B17: PNJ dialoguants éditables | C17: 16 PNJ/salle ; 64 PNJ/projet ; nom 80 caractères ; conduits refusés pour les corps PNJ, arrivées Mission non bloquées par ces conduits. | D17: Implémenté (borné) | E17: PNJ stationnaires de playtest ; pas de membre de campagne, cloud ou script libre.

Sheet 06_Sources
A1: Tantalus Frontier — V162
A2: 06_Sources
A3: Prépublication : implémentation et validation du commit restent distinctes.
A5: Source_ID | B5: Type | C5: Référence | D5: Portée | E5: Limite
A6: SRC-V146 | B6: Plan hérité | C6: docs/forge/xeno-trials/xeno-trials-plan-v146.json | D6: 189 IDs et les 40 présentations des quatre identités. | E6: Préproduction ; aucun kit canonique approuvé.
A7: SRC-V155 | B7: Suivi hérité | C7: docs/forge/xeno-trials/progress-v155.json | D7: 40 présentations et 28 tâches ART153 conservées. | E7: Les cellules de recette prépublication ne prouvent pas la CI.
A8: SRC-NATIVE | B8: Sources natives | C8: src/xeno-trials-rig-data-v154.js | D8: Quatre sprites V154 dont les empreintes sont inchangées. | E8: Ni capture de mouvement,ni dessin de parties cachées.
A9: SRC-AUDITS | B9: Audit technique | C9: docs/forge/V143-AUDIT-FIXES.md | D9: Sauvegardes,cache,commandes et limites restantes | E9: Pas certification des politiques cloud ni du matériel physique.
A10: SRC-POPULATION | B10: Contrats exécutables | C10: src/hub-annex-npc-life-v141.js | D10: 6 affectations initiales +15 rotations ; 19 annexes couvertes conditionnellement. | E10: Aucune nouvelle identité ni trajet continu interannexes.
A11: SRC-FORGE | B11: Contrat exécutable | C11: src/forge-narrative-v156.js | D11: Récits bornés, objets de récit et temps de simulation actif | E11: Pas de script libre ni inventaire de campagne ; checkpoint local suivi séparément.
A12: SRC-CHECKPOINT | B12: Contrat exécutable | C12: src/forge-playtest-checkpoint-v157.js | D12: Codec et checkpoint local explicite liés au projet et à son équipement. | E12: Pas de cloud Forge ni écriture de campagne.
A13: SRC-OPS-ACTIVE | B13: Registre utilisé par l’application | C13: src/special-operations-v131.js | D13: 21 accès jouables : 19 campagnes et 2 surfaces hub ; 20 partiels/1 effectif. | E13: Présence d’une route ne vaut pas campagne ou corpus artistique fini.
A14: SRC-EXIT | B14: Contrat exécutable | C14: src/xeno-trials-sequences-v155.js | D14: Retombée et sortie de rendu V157 séparées des 40 séquences/200 clés héritées ; identités de partie/tick autonomes. | E14: Quatre rigs natifs ; pas de locomotion complète ni certification 1:1.
A15: SRC-SUCCESSION | B15: Pont de vérification | C15: scripts/audit-succession-v157.mjs | D15: Documents V156 ancrés ; chaque transition old/new SHA et chaque source courante vérifiés. | E15: Pas de comparaison à des commits absents en CI shallow.
A16: SRC-NPCS-V158 | B16: Contrat exécutable | C16: src/forge-npcs-v158.js | D16: PNJ et récits éditables bornés dans les playtests Forge. | E16: Archive sandbox ancienne absente ; pas de cloud ni script libre.
... A34: C162-APC | B34: Périmètre hors Forge / demande existante | C34: src/campaign-convoy-history-v162.js ; src/campaign-convoy-history-ui-v162.js ; campaign-convoy-history-v162.css ; scripts/qa-campaign-convoy-history-v162.py | D34: Une archive compacte conserve au plus huit résultats APC natifs distincts, avec leurs relevés de distance, barrages, reine, blindage réel, protocole et trois lectures validées. L’admission exige le même identifiant d’opération, campagne, monde, numéro de résolution, déploiement et état terminal ; le succès exige son reçu complet, et l’échec ne conserve que le checkpoint partiel réel clairement désigné. L’identité V84 de l’opérateur est figée lorsqu’elle est valide ; les anciens retours peuvent rester anonymes. La consultation est en lecture seule et ne verse aucune récompense. | E34: Journal de huit retours au plus, pas campagne étendue, enregistrement vidéo ou nouveau canon. Seuls les vrais résultats admissibles sont capturés ; aucun résultat absent n’est inventé et la lecture ne rejoue pas de paiement.

Sheet 07_Recette
A1: Tantalus Frontier — V162
A2: 07_Recette
A3: Prépublication : implémentation et validation du commit restent distinctes.
A5: Contrôle_ID | B5: Commande / contrôle | C5: État prépublication | D5: Portée / limite
A6: QA162-NODE | B6: Suites Node déclarées et dédupliquées | C6: À exécuter sur le commit final | D6: Aucun total de recette V161 transféré.
A7: QA162-HARPOON | B7: scripts/verify-harpoon-unload-v162.mjs ; scripts/verify-weapon-actions-v131.mjs ; scripts/qa-harpoon-native-v162.py | C7: À exécuter sur le commit final | D7: Le défaut de fermeture et le vieux blocage d’achat V61 sont deux constats distincts. Aucun nouveau module d’arme, dessin ou source canonique. La recette des quatre variantes sur le commit final reste à exécuter ; les parcours initiaux ne sont pas transférés comme résultats finaux.
A8: QA162-AUDIO | B8: scripts/verify-audio-lifecycle-v162.mjs ; scripts/qa-audio-native-v162.py | C8: À exécuter sur le commit final | D8: Aucune nouvelle musique, voix, banque originale ou source de franchise. Le pilote Chromium headless active réellement un autre onglet et minimise la fenêtre, mais document.hidden n’y est pas observé : aucun parcours de scène masquée réussi n’est certifié. Un contrôle automatisé ne certifie pas le rendu sur haut-parleurs ou appareils physiques ; recette exacte à exécuter.
A9: QA162-CREW | B9: scripts/verify-npc-medical-route-v162.mjs ; scripts/qa-npc-medical-route-v162.py | C9: À exécuter sur le commit final | D9: Un circuit parent/annexe borné. Aucun ascenseur, déplacement physique entre ponts, nouveau dessin ou cycle de dos. Les soins, missions et autres priorités restent natifs ; le trajet après délégation n’est pas prouvé par ce lot.
A10: QA162-APC | B10: scripts/verify-campaign-convoy-history-v162.mjs ; scripts/qa-campaign-convoy-history-v162.py | C10: À exécuter sur le commit final | D10: Journal de huit retours au plus, pas campagne étendue, enregistrement vidéo ou nouveau canon. Seuls les vrais résultats admissibles sont capturés ; aucun résultat absent n’est inventé et la lecture ne rejoue pas de paiement.
A11: QA162-DOCUMENTS | B11: node --test scripts/verify-audit-continuation-v162.mjs | C11: À exécuter sur le commit final | D11: 68 tâches Trials, 189 identités, 16 classeurs historiques et Forge explicitement reportée.
A12: QA162-NATIVE | B12: Contrôles natifs, import Save déclaré et rechargements réels | C12: À vérifier séparément | D12: Recettes automatisées ; aucun participant humain ou contenu artistique 1:1 déclaré.
A13: QA162-RELEASE | B13: Paquet, CI, revue, fusion et publication | C13: À vérifier séparément | D13: Les résultats seront liés à leurs reçus réels, sans modifier les sources prépublication.

Sheet 08_Roster
A1: Tantalus Frontier — V162
A2: 08_Roster
A3: Prépublication : implémentation et validation du commit restent distinctes.
A5: ID exact | B5: Identité | C5: Famille | D5: Rig V154 | E5: Séquences V155 | F5: Fidélité approuvée
A6: warrior | B6: Warrior | C6: xenomorph | D6: 0 | E6: 0 | F6: 0
A7: runner | B7: Runner | C7: xenomorph | D7: 0 | E7: 0 | F7: 0
A8: arachnoid | B8: Arachnoid | C8: xenomorph | D8: 0 | E8: 0 | F8: 0
A9: defender | B9: Defender | C9: xenomorph | D9: 0 | E9: 0 | F9: 0
A10: grid | B10: Grid | C10: xenomorph | D10: 0 | E10: 0 | F10: 0
A11: spitter | B11: Spitter | C11: xenomorph | D11: 0 | E11: 0 | F11: 0
A12: prowler | B12: Prowler | C12: xenomorph | D12: 1 | E12: 10 | F12: 0
A13: razor-claws | B13: Razor Claws | C13: xenomorph | D13: 0 | E13: 0 | F13: 0
A14: chrysalis | B14: Chrysalis | C14: xenomorph | D14: 0 | E14: 0 | F14: 0
A15: smasher | B15: Smasher | C15: xenomorph | D15: 0 | E15: 0 | F15: 0
A16: predalien | B16: Predalien — Primal Hunt | C16: xenomorph | D16: 0 | E16: 0 | F16: 0
A17: xenoborg | B17: Xenoborg | C17: xenomorph | D17: 0 | E17: 0 | F17: 0
... A194: drive-v123-game-combat-synthetic-avp2 | B194: Combat Synthetic — unité désarmée — Altered | C194: synthetic | D194: 0 | E194: 0 | F194: 0

Sheet 09_AutresAudits
A1: Tantalus Frontier — V162
A2: 09_AutresAudits
A3: Prépublication : implémentation et validation du commit restent distinctes.
A5: Manque_ID | B5: Source | C5: État historique V156 | D5: État / dépendance V159 | E5: Clôture artistique
A6: encyclopedia-source | B6: Pont Excel V61/V63 et catalogue courant V62 ; audit V61 historique | C6: Source brute absente | D6: Classeur brut absent ; métadonnées du pont présentes (2363 entités globales, 2929 thématiques), 14 liens d’armes/3 de véhicules et catalogue jeu de 1329 entrées disponibles. Pas de revue du classeur brut. | E6: 0
A7: dlc-v10-archives | B7: Conversations de reprise | C7: Archives absentes | D7: DLC Blackout/Earth et sprites V10 non récupérés. | E7: 0
A8: trials-185-other | B8: Plan V146 / suivi V155 | C8: 185 IDs sans rigsV154/séquencesV155 | D8: Leurs mécaniques existantes restent distinctes de ce lot. | E8: 0
A9: trials-full-locomotion | B9: Suivis V148-V155 | C9: Ouvert | D9: Locomotion/combat/finishes/dessins complets restent à produire. | E9: 0
A10: forge-script-free | B10: Audit Forge | C10: Ouvert | D10: Les récits à terminaux ne constituent pas un langage de script libre. | E10: 0
A11: forge-cloud-progress | B11: Audit Forge | C11: Ouvert | D11: Checkpoint local explicite livré techniquement ; cloud Forge toujours ouvert. | E11: 0
A12: operations-active-registry | B12: SPECIAL_OPERATIONS_V131 | C12: V67 : 13 sans route | D12: V131 déjà actif : 21 accès jouables,20 partiels/1 effectif ; corpus et campagnes étendues restent ouverts. | E12: 0
A13: annex-interroom-travel | B13: Planning équipage | C13: 18 annexes ; pas de marche interannexes | D13: 19 affectations historiques ; premier circuit parent-annexe BISHOP laboratoire/baie synthétique ajouté V159. Autres routes, quarantaine, ponts et ascenseurs restent ouverts. | E13: 0
A14: costume-atlases | B14: Registre franchise V119 | C14: 30 sans atlas dédié | D14: Atlas et animations dédiés restent distincts du kit colonial modulaire existant. | E14: 0

Sheet 10_Operations
A1: Tantalus Frontier — V162
A2: 10_Operations
A3: Prépublication : implémentation et validation du commit restent distinctes.
A5: Opération_ID | B5: Titre | C5: Surface / route | D5: Statut technique | E5: Jouable | F5: Mécaniques / corpus restants | G5: Canon exact
A6: queen-mother-song | B6: LE CHANT DE LA REINE-MÈRE | C6: special-queen-mother-v131 | D6: partial | E6: 1 | F6: dedicated-queen-mother-animation; complete-royal-cast | G6: 0
A7: hive-world | B7: LV-XENO : LA RUCHE-MONDE | C7: special-hive-world-v131 | D7: partial | E7: 1 | F7: dedicated-planet-queen-art; complete-organ-biomes | G7: 0
A8: titan-equalizer | B8: TALOS CONTRE LE TITAN | C8: special-titan-v131 | D8: partial | E8: 1 | F8: dedicated-talos-titan-art; canonical-mega-loader-corpus | G8: 0
A9: narrative-collectables | B9: ARCHIVES NARRATIVES ÉTENDUES | C9: special-narrative-qz17 | D9: partial | E9: 1 | G9: 0
A10: alpha-bravo-coop | B10: DOCTRINE ALPHA / BRAVO | C10: special-alpha-bravo-doctrine | D10: partial | E10: 1 | G10: 0
A11: eloise-uncrowned-queen | B11: ÉLOÏSE : LA REINE SANS COURONNE | C11: special-eloise-v131 | D11: partial | E11: 1 | F11: dedicated-eloise-animation; hush-six-and-mother-hunter-art | G11: 0
A12: pangaea-second-extinction | B12: PANGAEA : LA SECONDE EXTINCTION | C12: special-pangaea-v131 | D12: partial | E12: 1 | F12: dedicated-dinosaur-and-sauria-art; complete-prehistoric-corpus | G12: 0
A13: atax-false-queen | B13: A.T.A.X.-Q : LA FAUSSE REINE | C13: special-atax-v131 | D13: partial | E13: 1 | F13: dedicated-regina-animation; complete-seven-sector-campaign | G13: 0
A14: alien-survival-systems | B14: SYSTÈMES DE SURVIE ALIEN | C14: special-alien-survival-systems | D14: effective | E14: 1 | G14: 0
A15: jeri-false-son | B15: JERI : LE FAUX FILS | C15: special-jeri-v131 | D15: partial | E15: 1 | F15: dedicated-jeri-and-saint-animation; complete-segmented-synthetic-art | G15: 0
A16: black-abyss | B16: OPÉRATION ABYSSE NOIR | C16: special-black-abyss-v131 | D16: partial | E16: 1 | F16: dedicated-hadal-manta-art; complete-aquatic-bestiary | G16: 0
A17: tantalus-hub-expansion | B17: USS TANTALUS — HUB COMMERCIAL | C17: hub | D17: partial | E17: 1 | F17: independent-prop-bitmaps; dedicated-annex-npcs; physical-training-exercises; physical-archive-replay; cctv-lockdown-controls | G17: 0
A18: bioforge | B18: BIOFORGE | C18: hub | D18: partial | E18: 1 | F18: full-enemy-roster; complete-dedicated-art-corpus | G18: 0
A19: protocol-z110 | B19: PROTOCOLE Z-110 | C19: special-z110-v131 | D19: partial | E19: 1 | F19: dedicated-z110-and-morrigan-art; complete-mecha-animation-corpus | G19: 0
A20: mire-archive-001 | B20: MIRE ARCHIVE 001 : NOSTROMO | C20: special-nostromo-v131 | D20: partial | E20: 1 | F20: complete-nostromo-cast; complete-historical-campaign | G20: 0
A21: broodstorm | B21: BROODSTORM | C21: special-broodstorm-v131 | D21: partial | E21: 1 | F21: dedicated-flying-queen-art; complete-modular-dropship-corpus | G21: 0
A22: black-cocoon | B22: COCON NOIR | C22: special-black-cocoon | D22: partial | E22: 1 | F22: dedicated-cocoon-bitmap-corpus; extended-survivor-campaign | G22: 0
A23: last-course-tantalus | B23: LA DERNIÈRE COURSE DE TANTALUS | C23: special-apc-convoy | D23: partial | E23: 1 | F23: local-convoy-coop | G23: 0
A24: cargo-brutal | B24: CARGO BRUTAL | C24: special-cargo-brutal | D24: partial | E24: 1 | F24: dedicated-cargo-matriarch-art | G24: 0
A25: c12-horde | B25: SAS C-12 · DÉFENSE | C25: special-c12-horde | D25: partial | E25: 1 | F25: extended-horde-campaign | G25: 0
A26: archive-relay | B26: ARCHIVES QZ-18 · RELAIS | C26: special-archive-relay | D26: partial | E26: 1 | F26: recorded-media-corpus | G26: 0

Sheet 11_Succession
A1: Tantalus Frontier — V162
A2: 11_Succession
A3: Prépublication : implémentation et validation du commit restent distinctes.
A5: Module | B5: SHA V158 | C5: SHA V159 | D5: Évolution volontaire | E5: Vérificateurs comportementaux
A6: index.html | B6: 84f22fb623d4d7bf5db5b2b55e9da70516ffc09ac0eacaad904b0cbd74bc240a | C6: 9cce9373641e8440201bf6d64cd5b48ae0dfcab7f7cc90c5fe6230e9d2c500e0 | D6: Charge la présentation dédiée du journal compact des retours APC depuis une feuille locale admise, en gardant les autres contrôles natifs et le déploiement inchangés. | E6: scripts/verify-campaign-convoy-history-v162.mjs ; scripts/verify-audit-v143.mjs
A7: src/app.js | B7: c4a2f8e5d5b9246c97fe9c9e357ce834c61307a609e0626565cff8f47cf80c5c | C7: ac0404430bb38a08b454bcc30a4d85a6af1f0afb57a953552739039cdc8180dd | D7: Capture le checkpoint de mission avant stop lors de la fermeture puis raccorde le service médical et l’archive compacte APC, sans modifier les modules Forge reportés. | E7: scripts/verify-harpoon-unload-v162.mjs ; scripts/verify-weapon-actions-v131.mjs ; scripts/verify-audio-lifecycle-v162.mjs ; scripts/verify-npc-medical-route-v162.mjs ; scripts/verify-campaign-convoy-history-v162.mjs
A8: src/npc-service-routes-v161.js | B8: 1571979e0dfe7d6bbad7e120aa1edae445099911909da0e7e3748e514674e189 | C8: 3bfd466c91a0861b1f99c806769a69a144942627c25fe2f1d47dcbd40711bf56 | D8: Expose la fabrique de circuits de service paramétrée et intègre le circuit médical indépendant, en préservant les propriétaires existants et les priorités natives. | E8: scripts/verify-npc-medical-route-v162.mjs
A9: src/save.js | B9: 59d429c858402a26a7768e47e6520aff95f6b6f12668f8bb69430502c8952e5d | C9: 98a20e4a0f52a7c33d5d3e53757ad4aba30cad350bacbe2fbac4aa8a6dc3403a | D9: Normalise la progression bornée du service médical et les huit comptes rendus APC admissibles en conservant les autres données natives et les schémas historiques. | E9: scripts/verify-npc-medical-route-v162.mjs ; scripts/verify-campaign-convoy-history-v162.mjs
A10: sw.js | B10: fd43d5989bde6df59643796d7a9c23fbfaa3e444bb07967f6d90b8cfba40b76d | C10: 0b506c1e7e57e36e50348d3a89400cc5976a65202b8830ef2163f9cde0c2e657 | D10: Admet les nouveaux modules et la feuille de présentation hors Forge dans le shell local avec un cache de continuation distinct, sans modifier les modules Forge reportés. | E10: scripts/verify-audit-v143.mjs ; scripts/verify-npc-medical-route-v162.mjs ; scripts/verify-campaign-convoy-history-v162.mjs
A11: campaign-convoy-history-v162.css | B11: Non épinglé en V161 | C11: 6f92b205b5c1970912e1051be0b6d6c3b2716acf27e767423a8d9c25b93806e2 | D11: Une archive compacte conserve au plus huit résultats APC natifs distincts, avec leurs relevés de distance, barrages, reine, blindage réel, protocole et trois lectures validées. L’admission exige le même identifiant d’opération, campagne, monde, numéro de résolution, déploiement et état terminal ; le succès exige son reçu complet, et l’échec ne conserve que le checkpoint partiel réel clairement désigné. L’identité V84 de l’opérateur est figée lorsqu’elle est valide ; les anciens retours peuvent rester anonymes. La consultation est en lecture seule et ne verse aucune récompense. | E11: scripts/verify-campaign-convoy-history-v162.mjs
A12: src/audio.js | B12: Non épinglé en V161 | C12: ce43a728dc9cc14a7f0b1b0226163c5434fdf1eb804e349a427abdaeeac0b5c2 | D12: Ajoute la garde de volume maître nul aux chemins d’effets décodés et de synthèse pour refuser toute admission sonore pendant la coupure, sans changer les médias ou mécanismes de transfert hérités. | E12: scripts/verify-audio-lifecycle-v162.mjs
A13: src/campaign-convoy-history-ui-v162.js | B13: Non épinglé en V161 | C13: e973c53c63ef8b425772ad049cab133b7052532be6956210e149174b3d940619 | D13: Une archive compacte conserve au plus huit résultats APC natifs distincts, avec leurs relevés de distance, barrages, reine, blindage réel, protocole et trois lectures validées. L’admission exige le même identifiant d’opération, campagne, monde, numéro de résolution, déploiement et état terminal ; le succès exige son reçu complet, et l’échec ne conserve que le checkpoint partiel réel clairement désigné. L’identité V84 de l’opérateur est figée lorsqu’elle est valide ; les anciens retours peuvent rester anonymes. La consultation est en lecture seule et ne verse aucune récompense. | E13: scripts/verify-campaign-convoy-history-v162.mjs
A14: src/campaign-convoy-history-v162.js | B14: Non épinglé en V161 | C14: 30acb584825844a348e37436b74fbb956e76a1ae7d2e4c1bb662587fec3fba31 | D14: Une archive compacte conserve au plus huit résultats APC natifs distincts, avec leurs relevés de distance, barrages, reine, blindage réel, protocole et trois lectures validées. L’admission exige le même identifiant d’opération, campagne, monde, numéro de résolution, déploiement et état terminal ; le succès exige son reçu complet, et l’échec ne conserve que le checkpoint partiel réel clairement désigné. L’identité V84 de l’opérateur est figée lorsqu’elle est valide ; les anciens retours peuvent rester anonymes. La consultation est en lecture seule et ne verse aucune récompense. | E14: scripts/verify-campaign-convoy-history-v162.mjs
A15: src/npc-medical-route-v162.js | B15: Non épinglé en V161 | C15: 389b2afae1898c6f6b675d9ebac116c936ce2e90c26fd5d09bbd94e39f00caa6 | D15: Expose la fabrique de circuits de service paramétrée et intègre le circuit médical indépendant, en préservant les propriétaires existants et les priorités natives. | E15: scripts/verify-npc-medical-route-v162.mjs

Sheet 12_TrialsSortie
A1: Tantalus Frontier — V162
A2: 12_TrialsSortie
A3: Prépublication : implémentation et validation du commit restent distinctes.
A5: Fighter_ID | B5: Contrat | C5: Déclenchement | D5: Déplacement | E5: Portée / limite | F5: État artistique | G5: Clôture | H5: Approuvé 1:1
A6: prowler | B6: native-spatial-exit-v157 | C6: Après phases de verdict admissibles ou retombée V157 autonome | D6: Retombée de rendu 180–600 ms si aérien ; puis trajet vers bord et appuis alternés | E6: Rig natif admis seulement ; corps physiques inchangés ; caméra fixe et appuis contrôlés ; pas de marche dessinée complète. Pause/skip/mouvement réduit respectés. | F6: Partiel | G6: 0 | H6: 0
A7: dd-darwin-era-cultist | B7: native-spatial-exit-v157 | C7: Après phases de verdict admissibles ou retombée V157 autonome | D7: Retombée de rendu 180–600 ms si aérien ; puis trajet vers bord et appuis alternés | E7: Rig natif admis seulement ; corps physiques inchangés ; caméra fixe et appuis contrôlés ; pas de marche dessinée complète. Pause/skip/mouvement réduit respectés. | F7: Partiel | G7: 0 | H7: 0
A8: import-game-dd-wy-commando | B8: native-spatial-exit-v157 | C8: Après phases de verdict admissibles ou retombée V157 autonome | D8: Retombée de rendu 180–600 ms si aérien ; puis trajet vers bord et appuis alternés | E8: Rig natif admis seulement ; corps physiques inchangés ; caméra fixe et appuis contrôlés ; pas de marche dessinée complète. Pause/skip/mouvement réduit respectés. | F8: Partiel | G8: 0 | H8: 0
A9: import-game-dd-guardian | B9: native-spatial-exit-v157 | C9: Après phases de verdict admissibles ou retombée V157 autonome | D9: Retombée de rendu 180–600 ms si aérien ; puis trajet vers bord et appuis alternés | E9: Rig natif admis seulement ; corps physiques inchangés ; caméra fixe et appuis contrôlés ; pas de marche dessinée complète. Pause/skip/mouvement réduit respectés. | F9: Partiel | G9: 0 | H9: 0

Sheet 13_Preuve1to1
A1: Tantalus Frontier — V162
A2: 13_Preuve1to1
A3: Prépublication : implémentation et validation du commit restent distinctes.
A5: ID exact | B5: Identité | C5: Œuvre déclarée | D5: Sources héritées | E5: Image du projet | F5: SHA image projet | G5: Édition œuvre fixée | H5: Timecode / page œuvre | I5: Capture œuvre approuvée | J5: Fidélité au projet — portée | K5: Œuvre approuvée 1:1 | L5: Preuve manquante
A6: warrior | B6: Warrior | C6: Aliens (1986) | D6: S01 | J6: Non évalué dans ce lot | K6: 0 | L6: Édition/build, métrage ou page et capture approuvée de l’œuvre non relevés.
A7: runner | B7: Runner | C7: Alien 3 (1992) | D7: S02 | J7: Non évalué dans ce lot | K7: 0 | L7: Édition/build, métrage ou page et capture approuvée de l’œuvre non relevés.
A8: arachnoid | B8: Arachnoid | C8: Alien vs. Predator — Capcom (1994) | D8: S16 | J8: Non évalué dans ce lot | K8: 0 | L8: Édition/build, métrage ou page et capture approuvée de l’œuvre non relevés.
A9: defender | B9: Defender | C9: Alien vs. Predator — Capcom (1994) | D9: R01 | J9: Non évalué dans ce lot | K9: 0 | L9: Édition/build, métrage ou page et capture approuvée de l’œuvre non relevés.
A10: grid | B10: Grid | C10: Alien vs. Predator (2004) | D10: R01 | J10: Non évalué dans ce lot | K10: 0 | L10: Édition/build, métrage ou page et capture approuvée de l’œuvre non relevés.
A11: spitter | B11: Spitter | C11: Aliens: Colonial Marines (2013) | D11: R01 | J11: Non évalué dans ce lot | K11: 0 | L11: Édition/build, métrage ou page et capture approuvée de l’œuvre non relevés.
A12: prowler | B12: Prowler | C12: Aliens: Fireteam Elite (2021) | D12: S08 | E12: /assets/user/castes-v87/game_afe_prowler.png | F12: 48edd1af2710048a065433b9e2c8dc20a03b05bc0a46a47394704f3a0c8bd544 | J12: Image du projet conservée ; geste adapté | K12: 0 | L12: Édition/build, métrage ou page et capture approuvée de l’œuvre non relevés.
A13: razor-claws | B13: Razor Claws | C13: Alien vs. Predator — Capcom (1994) | D13: S16 | J13: Non évalué dans ce lot | K13: 0 | L13: Édition/build, métrage ou page et capture approuvée de l’œuvre non relevés.
A14: chrysalis | B14: Chrysalis | C14: Alien vs. Predator — Capcom (1994) | D14: S16 | J14: Non évalué dans ce lot | K14: 0 | L14: Édition/build, métrage ou page et capture approuvée de l’œuvre non relevés.
A15: smasher | B15: Smasher | C15: Alien vs. Predator — Capcom (1994) | D15: R01 | J15: Non évalué dans ce lot | K15: 0 | L15: Édition/build, métrage ou page et capture approuvée de l’œuvre non relevés.
A16: predalien | B16: Predalien — Primal Hunt | C16: Aliens versus Predator 2: Primal Hunt (2002) | D16: R01 | J16: Non évalué dans ce lot | K16: 0 | L16: Édition/build, métrage ou page et capture approuvée de l’œuvre non relevés.
A17: xenoborg | B17: Xenoborg | C17: Aliens versus Predator (1999) | D17: S12 | J17: Non évalué dans ce lot | K17: 0 | L17: Édition/build, métrage ou page et capture approuvée de l’œuvre non relevés.
A18: royal-guard | B18: Royal Guard | C18: Alien vs. Predator — Capcom (1994) | D18: R01 | J18: Non évalué dans ce lot | K18: 0 | L18: Édition/build, métrage ou page et capture approuvée de l’œuvre non relevés.
A19: queen | B19: Reine mobile | C19: Aliens (1986) | D19: S01 | J19: Non évalué dans ce lot | K19: 0 | L19: Édition/build, métrage ou page et capture approuvée de l’œuvre non relevés.
A20: ravager | B20: Ravager | C20: Aliens vs. Predator: Extinction (2003) | D20: R01 | J20: Non évalué dans ce lot | K20: 0 | L20: Édition/build, métrage ou page et capture approuvée de l’œuvre non relevés.
A21: crusher-acm | B21: Crusher — ACM | C21: Aliens: Colonial Marines (2013) | D21: R01 | J21: Non évalué dans ce lot | K21: 0 | L21: Édition/build, métrage ou page et capture approuvée de l’œuvre non relevés.
A22: boiler | B22: Boiler | C22: Aliens: Colonial Marines (2013) | D22: R01 | J22: Non évalué dans ce lot | K22: 0 | L22: Édition/build, métrage ou page et capture approuvée de l’œuvre non relevés.
A23: burster | B23: Burster | C23: Aliens: Fireteam Elite (2021) | D23: S08 | J23: Non évalué dans ce lot | K23: 0 | L23: Édition/build, métrage ou page et capture approuvée de l’œuvre non relevés.
A24: stalker-arcade | B24: Stalker — arcade | C24: Alien vs. Predator — Capcom (1994) | D24: R01 | J24: Non évalué dans ce lot | K24: 0 | L24: Édition/build, métrage ou page et capture approuvée de l’œuvre non relevés.
... A148: import-game-afe2-bulwark | B148: Bulwark — adaptation | C148: Aliens: Fireteam Elite 2 (2026), build à relever | D148: S10 | J148: Non évalué dans ce lot | K148: 0 | L148: Édition/build, métrage ou page et capture approuvée de l’œuvre non relevés.
A149: import-game-dd-wy-commando | B149: Weyland-Yutani Commando — Altered — adaptation | C149: Aliens: Dark Descent (2023) | D149: R01 | E149: /assets/openai/sprites/static-game-v106/game-dd-wy-commando.png | F149: 1bcafd4c6b5e06611d0184c317f76422749d43e4b97a14f39316eef3eca3c012 | J149: Image du projet conservée ; geste adapté | K149: 0 | L149: Édition/build, métrage ou page et capture approuvée de l’œuvre non relevés.
A150: import-game-afe2-exploder | B150: Exploder — adaptation | C150: Aliens: Fireteam Elite 2 (2026), build à relever | D150: S11 | J150: Non évalué dans ce lot | K150: 0 | L150: Édition/build, métrage ou page et capture approuvée de l’œuvre non relevés.
A151: import-game-afe2-harbinger | B151: Harbinger — adaptation | C151: Aliens: Fireteam Elite 2 (2026), build à relever | D151: S11 | J151: Non évalué dans ce lot | K151: 0 | L151: Édition/build, métrage ou page et capture approuvée de l’œuvre non relevés.
A152: import-game-dd-synthetic | B152: Synthetic — adaptation | C152: Aliens: Dark Descent (2023) | D152: R01 | J152: Non évalué dans ce lot | K152: 0 | L152: Édition/build, métrage ou page et capture approuvée de l’œuvre non relevés.
A153: import-game-dd-guardian | B153: Guardian — Darwin Era — adaptation | C153: Aliens: Dark Descent (2023) | D153: R01 | E153: /assets/openai/sprites/static-game-v106/game-dd-guardian.png | F153: 9c78992ce49b080c73fef68a9813a1717970b5dae4be4e03d409a9876169d1c8 | J153: Image du projet conservée ; geste adapté | K153: 0 | L153: Édition/build, métrage ou page et capture approuvée de l’œuvre non relevés.
A154: synth-incinerator | B154: Synth Incinerator | C154: Aliens: Fireteam Elite (2021) | D154: S08, R03 | J154: Non évalué dans ce lot | K154: 0 | L154: Édition/build, métrage ou page et capture approuvée de l’œuvre non relevés.
A155: synth-detonator | B155: Synth Detonator | C155: Aliens: Fireteam Elite (2021) | D155: S08, R03 | J155: Non évalué dans ce lot | K155: 0 | L155: Édition/build, métrage ou page et capture approuvée de l’œuvre non relevés.
A156: synth-containment | B156: Synth Containment | C156: Aliens: Fireteam Elite (2021) | D156: S08, R03 | J156: Non évalué dans ce lot | K156: 0 | L156: Édition/build, métrage ou page et capture approuvée de l’œuvre non relevés.
A157: synth-enforcer | B157: Synth Enforcer | C157: Aliens: Fireteam Elite (2021) | D157: S08, R03 | J157: Non évalué dans ce lot | K157: 0 | L157: Édition/build, métrage ou page et capture approuvée de l’œuvre non relevés.
A158: afe2-engineer-hybrid | B158: Engineer hybrid — adaptation | C158: Aliens: Fireteam Elite 2 (2026), build à relever | D158: S11 | J158: Non évalué dans ce lot | K158: 0 | L158: Édition/build, métrage ou page et capture approuvée de l’œuvre non relevés.
A159: synth-peacekeeper | B159: Peacekeeper — adaptation | C159: Aliens: Fireteam Elite 2 (2026), build à relever | D159: S10 | J159: Non évalué dans ce lot | K159: 0 | L159: Édition/build, métrage ou page et capture approuvée de l’œuvre non relevés.
A160: afe2-spider | B160: Spider — adaptation | C160: Aliens: Fireteam Elite 2 (2026), build à relever | D160: S10 | J160: Non évalué dans ce lot | K160: 0 | L160: Édition/build, métrage ou page et capture approuvée de l’œuvre non relevés.
A161: afe2-igniter | B161: Igniter — interprétation | C161: Aliens: Fireteam Elite 2 (2026), build à relever | D161: S10 | J161: Non évalué dans ce lot | K161: 0 | L161: Édition/build, métrage ou page et capture approuvée de l’œuvre non relevés.
A162: afe2-bombardier | B162: Bombardier — interprétation | C162: Aliens: Fireteam Elite 2 (2026), build à relever | D162: S10 | J162: Non évalué dans ce lot | K162: 0 | L162: Édition/build, métrage ou page et capture approuvée de l’œuvre non relevés.
A163: afe2-huntsman | B163: Huntsman — interprétation | C163: Aliens: Fireteam Elite 2 (2026), build à relever | D163: S10 | J163: Non évalué dans ce lot | K163: 0 | L163: Édition/build, métrage ou page et capture approuvée de l’œuvre non relevés.
A164: import-xeno-titan-queen-nolegs | B164: Titan Queen NoLegs — reconstruction | C164: Pack 270926 — silhouette inférieure reconstruite pour la simulation | D164: R01 | J164: Non évalué dans ce lot | K164: 0 | L164: Édition/build, métrage ou page et capture approuvée de l’œuvre non relevés.
A165: synth-good-boy | B165: SunSpot « Good Boy » | C165: Alien: Into Charybdis et suites | D165: S18 | J165: Non évalué dans ce lot | K165: 0 | L165: Édition/build, métrage ou page et capture approuvée de l’œuvre non relevés.
... A167: synth-automated-powerloader | B167: Automated Power Loader | C167: Tantalus Frontier — conversion autonome de projet | D167: S01, R01 | J167: Non évalué dans ce lot | K167: 0 | L167: Édition/build, métrage ou page et capture approuvée de l’œuvre non relevés.
A168: dd-darwin-era-cultist | B168: Cultiste Darwin Era | C168: Aliens: Dark Descent (2023) | D168: R01 | E168: /assets/openai/sprites/static-game-v118/darwin-era-cultist.png | F168: 63ad74726db54f2943fed909f0027cb5d489a5f4ca58484b41871140219fa182 | J168: Image du projet conservée ; geste adapté | K168: 0 | L168: Édition/build, métrage ou page et capture approuvée de l’œuvre non relevés.
A169: drive-v123-acm-boiler | B169: Boiler — Altered | C169: Aliens: Colonial Marines (2013) | D169: R01 | J169: Non évalué dans ce lot | K169: 0 | L169: Édition/build, métrage ou page et capture approuvée de l’œuvre non relevés.
A170: drive-v123-acm-crusher | B170: Crusher — Altered | C170: Aliens: Colonial Marines (2013) | D170: R01 | J170: Non évalué dans ce lot | K170: 0 | L170: Édition/build, métrage ou page et capture approuvée de l’œuvre non relevés.
A171: drive-v123-afe-burster | B171: Burster — Altered | C171: Aliens: Fireteam Elite (2021) | D171: S08 | J171: Non évalué dans ce lot | K171: 0 | L171: Édition/build, métrage ou page et capture approuvée de l’œuvre non relevés.
A172: drive-v123-afe-prowler | B172: Prowler — Altered | C172: Aliens: Fireteam Elite (2021) | D172: S08 | J172: Non évalué dans ce lot | K172: 0 | L172: Édition/build, métrage ou page et capture approuvée de l’œuvre non relevés.
A173: drive-v123-afe-runner | B173: Runner — Altered | C173: Aliens: Fireteam Elite (2021) | D173: S08 | J173: Non évalué dans ce lot | K173: 0 | L173: Édition/build, métrage ou page et capture approuvée de l’œuvre non relevés.
A174: drive-v123-afe-spitter | B174: Spitter — Altered | C174: Aliens: Fireteam Elite (2021) | D174: S08 | J174: Non évalué dans ce lot | K174: 0 | L174: Édition/build, métrage ou page et capture approuvée de l’œuvre non relevés.
A175: drive-v123-comic-rogue-king | B175: Rogue — King — Altered | C175: Aliens: Rogue #1–4 | D175: S17 | J175: Non évalué dans ce lot | K175: 0 | L175: Édition/build, métrage ou page et capture approuvée de l’œuvre non relevés.
A176: drive-v123-creature-alien3-runner | B176: Runner — Dog Alien — Altered | C176: Alien 3 (1992) | D176: S02 | J176: Non évalué dans ce lot | K176: 0 | L176: Édition/build, métrage ou page et capture approuvée de l’œuvre non relevés.
A177: drive-v123-creature-aliens-queen-mobile | B177: Reine mobile — Altered | C177: Aliens (1986) | D177: S01 | J177: Non évalué dans ce lot | K177: 0 | L177: Édition/build, métrage ou page et capture approuvée de l’œuvre non relevés.
A178: drive-v123-creature-prometheus-engineer-biosuit | B178: Engineer — Combinaison biologique — Altered | C178: Prometheus (2012) | D178: S04 | J178: Non évalué dans ce lot | K178: 0 | L178: Édition/build, métrage ou page et capture approuvée de l’œuvre non relevés.
A179: drive-v123-creature-resurrection-newborn-v2 | B179: Newborn — Altered | C179: Alien Resurrection (1997) | D179: S03 | J179: Non évalué dans ce lot | K179: 0 | L179: Édition/build, métrage ou page et capture approuvée de l’œuvre non relevés.
A180: drive-v123-creature-romulus-offspring | B180: Offspring — Altered | C180: Alien: Romulus (2024) | D180: S06 | J180: Non évalué dans ce lot | K180: 0 | L180: Édition/build, métrage ou page et capture approuvée de l’œuvre non relevés.
... A194: drive-v123-game-combat-synthetic-avp2 | B194: Combat Synthetic — unité désarmée — Altered | C194: Aliens versus Predator 2 (2001) | D194: R01 | J194: Non évalué dans ce lot | K194: 0 | L194: Édition/build, métrage ou page et capture approuvée de l’œuvre non relevés.

Sheet 14_References
A1: Tantalus Frontier — V162
A2: 14_References
A3: Prépublication : implémentation et validation du commit restent distinctes.
A5: Source_ID | B5: Titre | C5: Nature | D5: État de consultation | E5: Consulté le | F5: Ce que la source établit | G5: Ce qu’elle ne prouve pas | H5: Repère | I5: URL
A6: R01 | B6: Roster et arènes du dépôt | C6: Code du projet | D6: Consultée | E6: 2026-10-16 | F6: IDs, variantes, origine déclarée, six arènes | G6: Un champ sourceWork ne prouve pas la fidélité d’un dessin. | H6: XENO_TRIALS_FIGHTERS_V96; XENO_TRIALS_STAGES_V96 | I6: https://github.com/darknigthmare/aliens-tantalus-frontier/blob/39bc11e5abe4427ae44c452e9727288e63310ec3/src/xeno-trials-data-v96.js
A7: R02 | B7: Moteur de duel | C7: Code du projet | D7: Consultée | E7: 2026-10-16 | F7: Attaques légères/lourdes/spéciales; rounds; simulation 120 Hz | G7: Les statistiques sont celles du projet, pas celles des films. | H7: XENO_TRIALS_ATTACKS_V96; finishRound; nextXenoTrialsRoundV96 | I7: https://github.com/darknigthmare/aliens-tantalus-frontier/blob/39bc11e5abe4427ae44c452e9727288e63310ec3/src/xeno-trials-engine-v96.js
A8: R03 | B8: Contrats synthétiques | C8: Code du projet | D8: Consultée | E8: 2026-10-16 | F8: Flammes, détonation, bouclier | G8: Ne confère pas automatiquement ces pouvoirs à tous les synthétiques. | H8: SYNTH_TRIAL_ATTACKS_V110 | I8: https://github.com/darknigthmare/aliens-tantalus-frontier/blob/39bc11e5abe4427ae44c452e9727288e63310ec3/src/synth-combat-v110.js
A9: R04 | B9: Échelles de présentation | C9: Code du projet | D9: Consultée | E9: 2026-10-16 | F9: Échelles et pivots existants | G9: Estimations du projet; tailles canoniques non certifiées. | H9: getXenoTrialsPhysicalScaleV119 | I9: https://github.com/darknigthmare/aliens-tantalus-frontier/blob/39bc11e5abe4427ae44c452e9727288e63310ec3/src/xeno-trials-physical-scale-v119.js
A10: S01 | B10: Aliens — fiche du distributeur | C10: Distributeur officiel | D10: Consultée | E10: 2026-10-16 | F10: Œuvre et référence filmique | G10: Ne documente pas un moveset ni les minutages des gestes. | H10: Texte public; métrage détaillé non relevé | I10: https://www.20thcenturystudios.com/movies/aliens
A11: S02 | B11: Alien 3 — fiche du distributeur | C11: Distributeur officiel | D11: Consultée | E11: 2026-10-16 | F11: Œuvre de référence du Runner | G11: Choisir version cinéma ou Assembly Cut; métrage non relevé. | H11: Texte public; métrage détaillé non relevé | I11: https://www.20thcenturystudios.com/movies/alien-3
A12: S03 | B12: Alien Resurrection — fiche du distributeur | C12: Distributeur officiel | D12: Consultée | E12: 2026-10-16 | F12: Œuvre de référence Newborn/Auriga | G12: Ne valide pas chaque coup proposé. | H12: Texte public; métrage détaillé non relevé | I12: https://www.20thcenturystudios.com/movies/alien-resurrection
A13: S04 | B13: Prometheus — fiche du distributeur | C13: Distributeur officiel | D13: Consultée | E13: 2026-10-16 | F13: Référence des Ingénieurs | G13: Ne certifie pas les tenues utilisateur ni un arsenal universel. | H13: Texte public; métrage détaillé non relevé | I13: https://www.20thcenturystudios.com/movies/prometheus
A14: S05 | B14: Alien Covenant — fiche du distributeur | C14: Distributeur officiel | D14: Consultée | E14: 2026-10-16 | F14: Œuvre de référence de David | G14: Chorégraphie et tenue à relever dans l’édition retenue. | H14: Texte public; métrage détaillé non relevé | I14: https://www.20thcenturystudios.com/movies/alien-covenant
A15: S06 | B15: Alien Romulus — fiche du distributeur | C15: Distributeur officiel | D15: Consultée | E15: 2026-10-16 | F15: Œuvre de référence Offspring | G15: Ne certifie ni durée des attaques ni locomotion de l’asset Altered. | H15: Texte public; métrage détaillé non relevé | I15: https://www.20thcenturystudios.com/movies/alien-romulus
A16: S07 | B16: Alien Isolation — manuel Feral | C16: Manuel officiel | D16: Consultée | E16: 2026-10-16 | F16: Commandes, Sevastopol, outils de survie | G16: Pas un catalogue exhaustif des animations Working Joe. | H16: Texte public; métrage détaillé non relevé | I16: https://www.feralinteractive.com/en/manuals/alienisolation/latest/steam/
... A70: H41 | B70: Référence héritée — Cultiste Darwin Era | C70: Référence héritée | D70: À vérifier | E70: 2026-10-16 | F70: dd-darwin-era-cultist | G70: Non consultée dans cette passe; ne pas promouvoir en preuve. | H70: Repris du registre du dépôt | I70: https://magazine.artstation.com/2023/07/tindalos-interactive-aliens-dark-descent-art-blast/

Sheet 15_LotsV159
A1: Tantalus Frontier — V162
A2: 15_LotsV159
A3: Prépublication : implémentation et validation du commit restent distinctes.
A5: Lot_ID | B5: Contrat | C5: IDs / périmètre | D5: État technique | E5: État recette | F5: Source / fidélité | G5: Reste ouvert
A6: bishop-annex-circulation | B6: Trajet physique laboratoire / baie synthétique | C6: crew-05-bishop-9 ; science-lab ↔ synthetic-bay ; pont 1 | D6: Implémenté (trajet borné ; réservation physique et marche native pendant le retrait d’alerte) | E6: À exécuter sur le commit publié | F6: Acteur,art, sols 2D et sas apparié natifs ; aucune nouvelle certification 1:1 | G6: Quarantaine, autres annexes, ponts, ascenseurs et corpus artistique complet.

Sheet 16_SourcesV159
A1: Tantalus Frontier — V162
A2: 16_SourcesV159
A3: Prépublication : implémentation et validation du commit restent distinctes.
A5: Source_ID | B5: Titre | C5: Auteur / éditeur | D5: URL consultée | E5: Consulté à (UTC) | F5: SHA256 contenu | G5: Portée | H5: Apport documenté | I5: Limite | J5: Mouvement certifié | K5: Approuvé1:1
A6: V159-REF-001 | B6: Aliens: Fireteam Elite | C6: Cold Iron Studios / official Aliens: Fireteam Elite site | D6: https://www.aliensfireteamelite.com/en/ | E6: 2026-10-18T07:37:40.412148+00:00 | F6: 762d7bd7c455435dab56d7ea4471cd574bc3878feeb7a7eddae3a48c1927ac9f | G6: identity and high-level game design | H6: Official overview of the launch-era game roster, cooperative context and classes. Counts are not a complete current expansion roster. | I6: No per-enemy choreography, frame counts, full DLC archive, or costume-specific film authenticity. | J6: 0 | K6: 0
A7: V159-REF-002 | B7: RELEASE NOTES | Aliens Fireteam Elite | C7: Cold Iron Studios / official release notes | D7: https://www.aliensfireteamelite.com/en/releasenotes/ | E7: 2026-10-18T07:39:51.046186+00:00 | F7: 8f6b7fb64cb00ac2bf718ecf2fcef44b65b38f1ada852607b00791868f6a948a | G7: capability / patch behavior | H7: Official acknowledgement of a grapple mechanic and implementation corrections. Prowler stumble behavior is also present in text. | I7: Does not give a full Prowler animation cycle, victim pin geometry, frame timing or per-species choreography. | J7: 0 | K7: 0
A8: V159-REF-003 | B8: Pathogen Deep Dive: An Exhilarating New Story | Aliens Fireteam Elite | C8: Cold Iron Studios; statements credited to Craig Zinkievich, Matt Highison and Chris Matz | D8: https://www.aliensfireteamelite.com/en/community/pathogen-deep-dive-an-exhilarating-new-story/ | E8: 2026-10-18T07:39:51.046530+00:00 | F8: 48cf8b7b7703729283ad0943e43dc9be29621ca019f2b4b216aff2677743d8e9 | G8: identity / named capabilities / art-direction commentary | H8: Named Brute ground impact/shockwaves and Queen clustered acid shots; descriptions of Pathogen Runner, Blight and the campaign are present. The same article classifies4C2 Astra as Rifle/Auto Rifle and describes repeating3-round bursts; this does not imply a current catalogue bug. | I8: No measured startup, active/recovery timing, projectile count or canonical2D choreography. Existing arena tuning remains simulation. | J8: 0 | K8: 0
A9: V159-REF-004 | B9: Crossplay, A New Game Mode, New Progression System & More Coming July 26th! | Aliens Fireteam Elite | C9: Cold Iron Studios / official Season4 announcement | D9: https://www.aliensfireteamelite.com/en/community/afe-season-4-announce/ | E9: 2026-10-18T07:39:51.047026+00:00 | F9: b013a8c4a0d37833df17903f68d75b7d4c9979167474b5fe0e50ccfa2a3165bf | G9: cosmetics taxonomy / weapon names | H9: Official cosmetic reward categories and named Season4 weapons; supports separating FTE cosmetics from1986 film costumes. The page names APEsuit Mk.3 and Seegson Maintenance overalls and the four listed Season4 weapons; names alone do not verify every visual detail. | I9: Does not identify every outfit in the project, prove a film-exact costume or provide a modular game sprite atlas. | J9: 0 | K9: 0
A10: V159-REF-005 | B10: ArtStation - Guardian Version.02 | C10: Raymond Sebastien, credited by the project OpenGraph author/title | D10: https://www.artstation.com/artwork/g0Va4P | E10: 2026-10-18T07:39:52.180824+00:00 | F10: 12c8d80269770773cc8fa3a6ce5f822cb7ed98fd95a875ac0371196ab09b7607 | G10: production concept identity / creator lore commentary | H10: Creator-authored Guardian Version.02 concept identity; description names Marlow, Darwin Era and Embryostatis. This is separate from the Fanatics/Androids/Commando project. | I10: Creator concept and final-design wording do not establish the final animated game model, attack timing, physical size or permission to reuse artwork. Full visual assets not certified by HTML metadata. | J10: 0 | K10: 0
A11: V159-REF-006 | B11: ArtStation - Ennemies for Aliens dark descent : The Fanatics, Androids, Weyland yutani Commando | C11: Raymond Sebastien, credited by the project OpenGraph author/title | D11: https://www.artstation.com/artwork/JvgEP0 | E11: 2026-10-18T07:39:52.467292+00:00 | F11: d8bb9b34ea2026e6233fcb2df142f9490b5d9e667b4cc79118b8709f76c94706 | G11: production concept identity / corpus distinction | H11: Creator project covers a selection of Fanatics concepts and names Androids/Weyland-Yutani Commando in its title. It cannot be silently substituted for Guardian Version.02. | I11: No specific concept sheet was visually re-reviewed through the HTML metadata alone; it does not automatically certify each roster row or final animation. | J11: 0 | K11: 0
A12: V159-REF-007 | B12: Tindalos Interactive Aliens: Dark Descent Art Blast - ArtStation Magazine | C12: Daniel Wade / ArtStation Magazine; showcase credits Tindalos Interactive artists | D12: https://magazine.artstation.com/2023/07/tindalos-interactive-aliens-dark-descent-art-blast/ | E12: 2026-10-18T07:39:52.512868+00:00 | F12: d3faca2a5061207234e3ea35515d7e43d7980db22bacddba9c9257ed43739180 | G12: production credit / concept provenance | H12: Production showcase independently credits Raymond Sebastien as a character concept artist for Aliens: Dark Descent. | I12: Showcase credit is not a frame-level animation reference, a complete final model roster, a measured size chart or a reuse licence. | J12: 0 | K12: 0
A13: V159-REF-008 | B13: Aliens: Dark Descent - Focus Entertainment Facebook Twitter Instagram Facebook Twitter Youtube Twitch Instagram | C13: Focus Entertainment / Tindalos Interactive /20th Century Studios | D13: https://www.focus-entmt.com/en/games/aliens-dark-descent | E13: 2026-10-18T07:39:52.728105+00:00 | F13: 21a9130573d9a329428a4dc71d37ff4f97ca9fa1da33231110afb95b211e5d9a | G13: game identity / publisher provenance | H13: Publisher-hosted game identity and developer/publisher credits. | I13: The retrieved server-rendered page contains limited descriptive text. No custom Blackout/Earth DLC archive or complete faction animation corpus is supplied. | J13: 0 | K13: 0
A14: V159-REF-009 | B14: Alien: Isolation™ - The Collection - manual | C14: Feral Interactive; original game by Creative Assembly / SEGA | D14: https://www.feralinteractive.com/en/manuals/alienisolation/latest/steam/ | E14: 2026-10-18T07:39:52.784320+00:00 | F14: b34ad1fbd9b69888fea05ee886fdf95278ce8018654c79c06ea0b5e06b79cd22 | G14: game/manual identity / qualitative stealth behavior | H14: Official Isolation manual documents corridors/ducts, crouching, concealment and noise mechanics in that game. | I14: This is Alien: Isolation, not Alien: Blackout. It does not recover the missing user-provided Blackout/Earth DLC archives or establish their contents. | J14: 0 | K14: 0
A15: V159-REF-010 | B15: Aliens | 20th Century Studios | C15: 20th Century Studios | D15: https://www.20thcenturystudios.com/movies/aliens | E15: 2026-10-18T07:39:53.205983+00:00 | F15: 29ac5109cfbdb1fcf53b9acb7e7a41e03a91ba6a2415ad51b5732be2c927c581 | G15: film identity / cast credit / published image metadata | H15: Official film identity, release date and cast credit list. The page also names a loader/Queen hero image in its alt text. | I15: The cast list does not map each actor to a role in the retrieved text and does not certify each Hicks/Hudson/Vasquez modular piece. Remote image/video frames were not inferred from alt text. | J15: 0 | K15: 0
A16: V159-REF-011 | B16: Characters - Raymond SEBASTIEN Character Concept Artist | C16: Raymond Sebastien / current artist site | D16: https://raymondsebastien.com/characters/ | E16: 2026-10-18T07:39:52.177917+00:00 | F16: 0447fa116399b05a8b48e46cc671b370f2a68df52c451ae8c6a58c4bcda3846e | G16: creator attribution / current portfolio navigation | H16: Current artist portfolio navigation and attribution are accessible; a Marlow entry is present. Historical/projects/g0Va4P andJvgEP0 URLs remain404. | I16: Current portfolio page does not itself replace the missing historical concept pages or supply a complete Dark Descent model/animation archive. | J16: 0 | K16: 0
A17: V159-REF-012 | B17: Guardian Version.02 — public project metadata | C17: Raymond Sebastien (sebray) | D17: https://www.artstation.com/projects/g0Va4P.json | E17: 2026-10-18T07:43:13.058039+00:00 | F17: 43411c6a10c7c14aa4cd6845c1f266474cba6379818ac786a99f4a58ede3d5d3 | G17: creator project identity / exact asset index / captioned concept-versus-in-game-still distinction | H17: Public project metadata identifies a Guardian final-model sheet and a separate in-game Guardian still credited to Tamás Kerti; it also lists attitude/scene concept art. | I17: The four ArtStation CDN image requests are still CONNECT403. Captions were read, but their image pixels were not viewed or certified and no motion cycle/timecode follows from them. | J17: 0 | K17: 0
... A20: V159-REF-015 | B20: Official Pathogen weapon reference grid | C20: Cold Iron Studios /20th Century Studios | D20: https://www.aliensfireteamelite.com/images/uploads/7c1e86e6cde1368364bb3f0cdbeed260.jpg | E20: 2026-10-18T07:43:13.059144+00:00 | F20: 98a64bac9cbd09b69e9137b4c1a22b46e9e58d215b78e93e6cf95c579095912d | G20: official weapon identity / static silhouette comparison | H20: All four printed weapon names and distinct still silhouettes are actually readable in the downloaded official image. These correspond to project IDs160,161,172,173. | I20: This image does not establish dimensions, grip/muzzle pivots, reload animation, rates, ammunition, full material accuracy or1:1 generated sprites. | J20: 0 | K20: 0

Sheet 17_LiensV159
A1: Tantalus Frontier — V162
A2: 17_LiensV159
A3: Prépublication : implémentation et validation du commit restent distinctes.
A5: ID exact | B5: Type | C5: Combattant_ID | D5: SourcesV159 | E5: Sources héritées | F5: Besoin / identité | G5: État historique prépublicationV158 | H5: Apport de référence | I5: Reste ouvert | J5: Fichier du projet | K5: SHA256 image du projet | L5: Clôture artistique | M5: Approuvé1:1
A6: prowler::intro | B6: Tâche Excel héritée | C6: prowler | D6: V159-REF-001 ; V159-REF-002 | E6: S08 | F6: Intro standard | G6: Raccordé techniquement ; art partiel | H6: AFE1 identifié ; notes officielles attestent le mécanisme général de grapple. Pas de clipProwler complet mesuré. | I6: Entrée V155 conservée sur le rig natif. Adaptation de simulation ; dessins complets, audio et relevés d’œuvre restent ouverts. Aucun lot artistique clos ni certification 1:1. | J6: /assets/user/castes-v87/game_afe_prowler.png | K6: 48edd1af2710048a065433b9e2c8dc20a03b05bc0a46a47394704f3a0c8bd544 | L6: 0 | M6: 0
A7: prowler::intro-rival | B7: Tâche Excel héritée | C7: prowler | D7: V159-REF-001 ; V159-REF-002 | E7: S08 | F7: Intro de rivalité | G7: Raccordé techniquement ; art partiel | H7: AFE1 identifié ; notes officielles attestent le mécanisme général de grapple. Pas de clipProwler complet mesuré. | I7: Réponse à la famille effective de l’adversaire, y compris hybride, pendant sa présentation ; aucune rivalité historique affirmée. Adaptation de simulation ; dessins complets, audio et relevés d’œuvre restent ouverts. Aucun lot artistique clos ni certification 1:1. | J7: /assets/user/castes-v87/game_afe_prowler.png | K7: 48edd1af2710048a065433b9e2c8dc20a03b05bc0a46a47394704f3a0c8bd544 | L7: 0 | M7: 0
A8: prowler::outro | B8: Tâche Excel héritée | C8: prowler | D8: V159-REF-001 ; V159-REF-002 | E8: S08 | F8: Outro | G8: Raccordé techniquement ; art partiel | H8: AFE1 identifié ; notes officielles attestent le mécanisme général de grapple. Pas de clipProwler complet mesuré. | I8: V157 ajoute une retombée de rendu bornée si le verdict fige le rig en l’air, puis une sortie vers les bords. Corps physiques et verdict inchangés ; phases historiques au sol intactes. Dessins, audio et revue 1:1 restent ouverts. | J8: /assets/user/castes-v87/game_afe_prowler.png | K8: 48edd1af2710048a065433b9e2c8dc20a03b05bc0a46a47394704f3a0c8bd544 | L8: 0 | M8: 0
A9: prowler::win-r1 | B9: Tâche Excel héritée | C9: prowler | D9: V159-REF-001 ; V159-REF-002 | E9: S08 | F9: Victoire de première manche | G9: Raccordé techniquement ; art partiel | H9: AFE1 identifié ; notes officielles attestent le mécanisme général de grapple. Pas de clipProwler complet mesuré. | I9: Réaction V155 réversible de victoire de manche conservée. Adaptation de simulation ; dessins complets, audio et relevés d’œuvre restent ouverts. Aucun lot artistique clos ni certification 1:1. | J9: /assets/user/castes-v87/game_afe_prowler.png | K9: 48edd1af2710048a065433b9e2c8dc20a03b05bc0a46a47394704f3a0c8bd544 | L9: 0 | M9: 0
A10: prowler::lose-r1 | B10: Tâche Excel héritée | C10: prowler | D10: V159-REF-001 ; V159-REF-002 | E10: S08 | F10: Défaite de première manche | G10: Raccordé techniquement ; art partiel | H10: AFE1 identifié ; notes officielles attestent le mécanisme général de grapple. Pas de clipProwler complet mesuré. | I10: Récupération V155 réversible de défaite de manche conservée. Adaptation de simulation ; dessins complets, audio et relevés d’œuvre restent ouverts. Aucun lot artistique clos ni certification 1:1. | J10: /assets/user/castes-v87/game_afe_prowler.png | K10: 48edd1af2710048a065433b9e2c8dc20a03b05bc0a46a47394704f3a0c8bd544 | L10: 0 | M10: 0
A11: prowler::win-final | B11: Tâche Excel héritée | C11: prowler | D11: V159-REF-001 ; V159-REF-002 | E11: S08 | F11: Victoire finale | G11: Raccordé techniquement ; art partiel | H11: AFE1 identifié ; notes officielles attestent le mécanisme général de grapple. Pas de clipProwler complet mesuré. | I11: Pose V155 de victoire terminale conservée ; aucun second résultat ni paiement. Adaptation de simulation ; dessins complets, audio et relevés d’œuvre restent ouverts. Aucun lot artistique clos ni certification 1:1. | J11: /assets/user/castes-v87/game_afe_prowler.png | K11: 48edd1af2710048a065433b9e2c8dc20a03b05bc0a46a47394704f3a0c8bd544 | L11: 0 | M11: 0
A12: prowler::lose-final | B12: Tâche Excel héritée | C12: prowler | D12: V159-REF-001 ; V159-REF-002 | E12: S08 | F12: Défaite finale | G12: Raccordé techniquement ; art partiel | H12: AFE1 identifié ; notes officielles attestent le mécanisme général de grapple. Pas de clipProwler complet mesuré. | I12: Pose V155 de défaite terminale conservée ; ce n’est pas une chute complète. Adaptation de simulation ; dessins complets, audio et relevés d’œuvre restent ouverts. Aucun lot artistique clos ni certification 1:1. | J12: /assets/user/castes-v87/game_afe_prowler.png | K12: 48edd1af2710048a065433b9e2c8dc20a03b05bc0a46a47394704f3a0c8bd544 | L12: 0 | M12: 0
A13: prowler::draw | B13: Tâche Excel héritée | C13: prowler | D13: V159-REF-001 ; V159-REF-002 | E13: S08 | F13: Égalité | G13: Raccordé techniquement ; art partiel | H13: AFE1 identifié ; notes officielles attestent le mécanisme général de grapple. Pas de clipProwler complet mesuré. | I13: Réaction sans vainqueur sur égalité réelle de manche ou de match ; ne force aucun résultat. Adaptation de simulation ; dessins complets, audio et relevés d’œuvre restent ouverts. Aucun lot artistique clos ni certification 1:1. | J13: /assets/user/castes-v87/game_afe_prowler.png | K13: 48edd1af2710048a065433b9e2c8dc20a03b05bc0a46a47394704f3a0c8bd544 | L13: 0 | M13: 0
A14: prowler::taunt | B14: Tâche Excel héritée | C14: prowler | D14: V159-REF-001 ; V159-REF-002 | E14: S08 | F14: Provocation | G14: Raccordé techniquement ; art partiel | H14: AFE1 identifié ; notes officielles attestent le mécanisme général de grapple. Pas de clipProwler complet mesuré. | I14: Commande T ou bouton DÉFI pendant le combat ; le bouton rend le focus au canvas quand le combat accepte les commandes. Annulation par déplacement, attaque, garde ou impact. Adaptation de simulation ; dessins complets, audio et relevés d’œuvre restent ouverts. Aucun lot artistique clos ni certification 1:1. | J14: /assets/user/castes-v87/game_afe_prowler.png | K14: 48edd1af2710048a065433b9e2c8dc20a03b05bc0a46a47394704f3a0c8bd544 | L14: 0 | M14: 0
A15: prowler::rematch | B15: Tâche Excel héritée | C15: prowler | D15: V159-REF-001 ; V159-REF-002 | E15: S08 | F15: Début de manche suivante | G15: Raccordé techniquement ; art partiel | H15: AFE1 identifié ; notes officielles attestent le mécanisme général de grapple. Pas de clipProwler complet mesuré. | I15: Reprise visuelle pendant le décompte existant des manches suivantes, sans nouvel équipement ni changement physique. Adaptation de simulation ; dessins complets, audio et relevés d’œuvre restent ouverts. Aucun lot artistique clos ni certification 1:1. | J15: /assets/user/castes-v87/game_afe_prowler.png | K15: 48edd1af2710048a065433b9e2c8dc20a03b05bc0a46a47394704f3a0c8bd544 | L15: 0 | M15: 0
A16: ART153-01 | B16: Tâche Excel héritée | C16: prowler | D16: V159-REF-001 ; V159-REF-002 | E16: S08 | F16: Références de poses et timecodes | G16: À relever | H16: AFE1 identifié ; notes officielles attestent le mécanisme général de grapple. Pas de clipProwler complet mesuré. | I16: Coordonnées mesurées sur le sprite du projet ; référence d’œuvre et timecodes non relevés. | J16: /assets/user/castes-v87/game_afe_prowler.png | K16: 48edd1af2710048a065433b9e2c8dc20a03b05bc0a46a47394704f3a0c8bd544 | L16: 0 | M16: 0
A17: ART153-02 | B17: Tâche Excel héritée | C17: prowler | D17: V159-REF-001 ; V159-REF-002 | E17: S08 | F17: Rig et points de contact | G17: Implémenté (adaptation) | H17: AFE1 identifié ; notes officielles attestent le mécanisme général de grapple. Pas de clipProwler complet mesuré. | I17: Rig exact, maillage, points de contact et appuis ; source native inchangée. Validation canonique non acquise. | J17: /assets/user/castes-v87/game_afe_prowler.png | K17: 48edd1af2710048a065433b9e2c8dc20a03b05bc0a46a47394704f3a0c8bd544 | L17: 0 | M17: 0
... A77: dd-darwin-era-cultist | B77: Identité roster existante | C77: dd-darwin-era-cultist | D77: V159-REF-006 ; V159-REF-013 ; V159-REF-007 | E77: H40 ; H41 | F77: Référence de l’identité exacte, sans fusion de variantes | G77: Art adapté ; aucune fidélité1:1 approuvée | H77: Corpus Fanatics/Androids/Commando : croquis Fanatics64738238 et Commando65093027. Contient aussi GuardianV01 abandonné65092845, jugé trop mutant par l’auteur, distinct de Version.02. La figure précise du PNG projet n’est pas réévaluée visuellement dans cette reprise. | I77: Édition/build ou concept exact, page/timecodes, capture approuvée, dessins cachés et revue comparative ; art complet et certification 1:1 ouverts. | J77: /assets/openai/sprites/static-game-v118/darwin-era-cultist.png | K77: 63ad74726db54f2943fed909f0027cb5d489a5f4ca58484b41871140219fa182 | L77: 0 | M77: 0
A78: drive-v123-fte-pathogen-brute-profile-v13 | B78: Identité roster existante | C78: drive-v123-fte-pathogen-brute-profile-v13 | D78: V159-REF-003 | E78: S09 | F78: Pathogen Brute | G78: Source d’identité/capacité seulement | H78: Identité nommée et capacités qualitatives du texte officiel ; aucun timing mesuré. | I78: Atlas/mouvements, comparaison au PNG projet, animation et approbation1:1 restent ouverts. | L78: 0 | M78: 0
A79: drive-v123-fte-pathogen-queen-right-v13 | B79: Identité roster existante | C79: drive-v123-fte-pathogen-queen-right-v13 | D79: V159-REF-003 ; V159-REF-014 | E79: S09 | F79: Pathogen Queen | G79: Source d’identité/capacité seulement | H79: Identité nommée et capacités qualitatives du texte officiel ; aucun timing mesuré. Image officielle revue : taille indiquée approximativement4,25m en posture voûtée ; indication diégétique approximative, sans redimensionnement du runtime. | I79: Atlas/mouvements, comparaison au PNG projet, animation et approbation1:1 restent ouverts. | L79: 0 | M79: 0
A80: drive-v123-fte-pathogen-runner-nodules-v13 | B80: Identité roster existante | C80: drive-v123-fte-pathogen-runner-nodules-v13 | D80: V159-REF-003 | E80: S09 | F80: Pathogen Runner | G80: Source d’identité/capacité seulement | H80: Identité nommée et capacités qualitatives du texte officiel ; aucun timing mesuré. | I80: Atlas/mouvements, comparaison au PNG projet, animation et approbation1:1 restent ouverts. | L80: 0 | M80: 0
A81: franchise-fireteam-ape-mk3 | B81: Costume existant — nom prouvé | D81: V159-REF-004 | E81: Registre franchiseV119 | F81: APEsuit Mk.3 | G81: Atlas dédié manquant ; non équipable | H81: Nom de la tenue dans le texte officiel Saison4. Aucun pixel modulaire ni validation de costume filmique produit. | I81: Atlas dédiés, états utiles, pivots, alpha, compatibilité des opérateurs et recette visuelle restent à produire. | J81: src/franchise-costumes-v119.js | L81: 0 | M81: 0
A82: franchise-fireteam-seegson-maintenance | B82: Costume existant — nom prouvé | D82: V159-REF-004 | E82: Registre franchiseV119 | F82: Seegson Maintenance overalls | G82: Atlas dédié manquant ; non équipable | H82: Nom de la tenue dans le texte officiel Saison4. Aucun pixel modulaire ni validation de costume filmique produit. | I82: Atlas dédiés, états utiles, pivots, alpha, compatibilité des opérateurs et recette visuelle restent à produire. | J82: src/franchise-costumes-v119.js | L82: 0 | M82: 0
A83: weapon-163-svat-92-sokol | B83: Arme existante — identité prouvée | D83: V159-REF-004 | E83: RegistresV121/V122 | F83: SVAT-92 Sokol | G83: static-pose-action-animation-missing | H83: Nom dans le texte officiel ; aucun relevé animé. | I83: Mouvement complet et comparaison1:1 non acquis ; statistiques et comportement de simulation conservés. | J83: src/weapon-catalog-additions-v121.js | L83: 0 | M83: 0
A84: weapon-165-m51-breaching-scattergun | B84: Arme existante — identité prouvée | D84: V159-REF-004 | E84: RegistresV121/V122 | F84: M51 Breaching Scattergun | G84: static-pose-action-animation-missing | H84: Nom dans le texte officiel ; aucun relevé animé. | I84: Mouvement complet et comparaison1:1 non acquis ; statistiques et comportement de simulation conservés. | J84: src/weapon-catalog-additions-v121.js | L84: 0 | M84: 0
A85: weapon-166-p649-hel | B85: Arme existante — identité prouvée | D85: V159-REF-004 | E85: RegistresV121/V122 | F85: P.649 HEL | G85: static-pose-action-animation-missing | H85: Nom dans le texte officiel ; aucun relevé animé. | I85: Mouvement complet et comparaison1:1 non acquis ; statistiques et comportement de simulation conservés. | J85: src/weapon-catalog-additions-v121.js | L85: 0 | M85: 0
A86: weapon-167-dkt-59-misha | B86: Arme existante — identité prouvée | D86: V159-REF-004 | E86: RegistresV121/V122 | F86: DKT-59 Misha | G86: static-pose-action-animation-missing | H86: Nom dans le texte officiel ; aucun relevé animé. | I86: Mouvement complet et comparaison1:1 non acquis ; statistiques et comportement de simulation conservés. | J86: src/weapon-catalog-additions-v121.js | L86: 0 | M86: 0
A87: weapon-160-eds-93-zadak | B87: Arme existante — identité prouvée | D87: V159-REF-003 ; V159-REF-015 | E87: RegistresV121/V122 | F87: EDS-93 Zadak Plasma Discharger | G87: static-pose-action-animation-missing | H87: Nom et silhouette dans la grille officielle réellement revue ; pas de mouvement. | I87: Mouvement complet et comparaison1:1 non acquis ; statistiques et comportement de simulation conservés. | J87: src/weapon-catalog-additions-v121.js | L87: 0 | M87: 0
A88: weapon-161-thunderbolt-mk2 | B88: Arme existante — identité prouvée | D88: V159-REF-003 ; V159-REF-015 | E88: RegistresV121/V122 | F88: Thunderbolt Mk.2 Autocannon | G88: static-pose-action-animation-missing | H88: Nom et silhouette dans la grille officielle réellement revue ; pas de mouvement. | I88: Mouvement complet et comparaison1:1 non acquis ; statistiques et comportement de simulation conservés. | J88: src/weapon-catalog-additions-v121.js | L88: 0 | M88: 0
A89: weapon-172-lem-stg24-storm-rifle | B89: Arme existante — identité prouvée | D89: V159-REF-003 ; V159-REF-015 | E89: RegistresV121/V122 | F89: LEM StG24 Storm Rifle | G89: static-pose-action-animation-missing | H89: Nom et silhouette dans la grille officielle réellement revue ; pas de mouvement. | I89: Mouvement complet et comparaison1:1 non acquis ; statistiques et comportement de simulation conservés. | J89: src/weapon-catalog-weapons-v122.js | L89: 0 | M89: 0
A90: weapon-173-u1a2-gl-conversion | B90: Arme existante — identité prouvée | D90: V159-REF-003 ; V159-REF-015 | E90: RegistresV121/V122 | F90: U1A2 GL Conversion | G90: static-pose-action-animation-missing | H90: Nom et silhouette dans la grille officielle réellement revue ; pas de mouvement. | I90: Mouvement complet et comparaison1:1 non acquis ; statistiques et comportement de simulation conservés. | J90: src/weapon-catalog-weapons-v122.js | L90: 0 | M90: 0
A91: weapon-174-4c2-astra | B91: Arme existante — identité prouvée | D91: V159-REF-003 | E91: RegistresV121/V122 | F91: 4C2 Astra | G91: static-pose-action-animation-missing | H91: Texte officiel : Rifle, Auto Rifle / repeating3-round burst. CatalogueV122 déjà rifle/burst ; ancienne tableV120 classehandgun : écart documentaire, pas défaut de gameplay démontré. | I91: Mouvement complet et comparaison1:1 non acquis ; statistiques et comportement de simulation conservés. | J91: src/weapon-catalog-weapons-v122.js | L91: 0 | M91: 0
A92: trials-presentation-unmapped | B92: Priorité du suivi | D92: V159-REF-005 ; V159-REF-006 ; V159-REF-012 ; V159-REF-013 ; V159-REF-002 | E92: PrioritesV158 | F92: Conserver les 40 raccordements et terminer leur art | G92: 40 raccordements techniques conservés ; art partiel | H92: Ces consultations précisent la provenance et les identités seulement ; le statut du chantier V158 reste inchangé. | I92: La sortie spatiale est maintenant suivie séparément sur quatre rigs ; les 40 séquences/200 clés héritées ne changent pas. Dessins, audio et revue restent ouverts. | L92: 0 | M92: 0
A93: trials-capture-human | B93: Priorité du suivi | D93: V159-REF-005 ; V159-REF-006 ; V159-REF-012 ; V159-REF-013 ; V159-REF-002 | E93: PrioritesV158 | F93: Continuer la capture après les trois réceptions humaines natives | G93: Prépublication : ART153-10/17/24 en adaptation native ; chorégraphie de simulation | H93: Ces consultations précisent la provenance et les identités seulement ; le statut du chantier V158 reste inchangé. | I93: Les trois réceptions visent des PNG natifs exacts ; leur chorégraphie demeure une simulation. Mise au sol complète, pin, corpus artistique et certification 1:1 restent ouverts. | L93: 0 | M93: 0
A94: trials-reference-and-art | B94: Priorité du suivi | D94: V159-REF-005 ; V159-REF-006 ; V159-REF-012 ; V159-REF-013 ; V159-REF-002 | E94: PrioritesV158 | F94: Compléter dessins, audio et preuves d’œuvre des quatre identités | G94: Ouvert artistiquement ; zéro clôture et zéro certification 1:1 | H94: Ces consultations précisent la provenance et les identités seulement ; le statut du chantier V158 reste inchangé. | I94: Le registre 189 IDs distingue image projet et preuve d’œuvre. Les 65 fiches V146 restent des consultations historiques, sans nouvelle consultation attribuée à V158. | L94: 0 | M94: 0
A95: trials-roster-extension | B95: Priorité du suivi | D95: V159-REF-005 ; V159-REF-006 ; V159-REF-012 ; V159-REF-013 ; V159-REF-002 | E95: PrioritesV158 | F95: Étendre les rigs et mouvements au reste du roster | G95: 185 identités hors de ce lot de rigs/séquences | H95: Ces consultations précisent la provenance et les identités seulement ; le statut du chantier V158 reste inchangé. | I95: 189 IDs conservés ; quatre rigs et 40 séquences cumulatives V156. Les 185 autres gardent leurs mécaniques précédentes, sans ces rigs et séquences. | L95: 0 | M95: 0
A96: trials-remaining-pilot-art | B96: Priorité du suivi | D96: V159-REF-005 ; V159-REF-006 ; V159-REF-012 ; V159-REF-013 ; V159-REF-002 | E96: PrioritesV158 | F96: Produire clips, locomotion, finitions des pilotes V148/V151/V152 | G96: Ouvert / recouvrement historique | H96: Ces consultations précisent la provenance et les identités seulement ; le statut du chantier V158 reste inchangé. | I96: 35 lots V148 et 28 lots V151 ne sont pas clos par les correctifs de gameplay; les versions du suivi se recouvrent. Ne pas additionner les tâches comme des demandes nouvelles. | L96: 0 | M96: 0
A97: costume-art | B97: Priorité du suivi | D97: V159-REF-004 | E97: PrioritesV158 | F97: Conserver le kit colonial disponible et produire les atlas franchise manquants | G97: Prépublication : warmup des textures borné à 16 ; 30 atlas franchise restent absents | H97: Ces consultations précisent la provenance et les identités seulement ; le statut du chantier V158 reste inchangé. | I97: Le graphe courant des actions, transits, opérateurs et pickup est prioritaire ; le warmup sélectionné du kit, du fallback et des poses futures utilise seulement les places restantes jusqu’à 16. Retain/start restent synchrones sans attendre le décodage ; aucune garantie pendant chargement, échec d’image ou pression maximale. Aucun nouveau pixel ni canon. | L97: 0 | M97: 0
A98: excel-identity-and-motion | B98: Priorité du suivi | E98: PrioritesV158 | F98: Résoudre identités ambiguës et animations du pont Excel | G98: Ne pas réouvrir les images fixes déjà livrées | H98: Ces consultations précisent la provenance et les identités seulement ; le statut du chantier V158 reste inchangé. | I98: Harpoon prêt V63. 4 entrées d’armes et3 véhicules du pont conservent une réserve; certaines illustrations natives V112+ existent seulement en pose fixe. | L98: 0 | M98: 0
A99: master-encyclopedia-source | B99: Priorité du suivi | E99: PrioritesV158 | F99: Récupérer le classeur brut sans perdre les registres disponibles | G99: Classeur brut absent ; métadonnées et catalogue du jeu disponibles | H99: Aucune archiveDLC ou fichierExcel brut récupéré. FeralIsolation ne prouve pasBlackout ; les imagesEarth présentes ne sont pas le DLC. | I99: Le pont Excel conserve 19 feuilles, les comptes 2363/2929 et 14 liens d’armes/3 de véhicules ; le catalogue du jeu contient 1329 entrées. Ce ne sont ni le fichier brut, ni la preuve d’un registre exhaustif de 2363 lignes récupéré. | L99: 0 | M99: 0
A100: dlc-v10-sources | B100: Priorité du suivi | E100: PrioritesV158 | F100: Récupérer archives de DLC Blackout/Earth et sprites V10 | G100: Sources absentes | H100: Aucune archiveDLC ou fichierExcel brut récupéré. FeralIsolation ne prouve pasBlackout ; les imagesEarth présentes ne sont pas le DLC. | I100: Absentes du workspace restauré et des noms d’archives versionnées inspectés. Mentions de sauvegarde Blackout ne prouvent pas les contenus DLC. | L100: 0 | M100: 0
A101: campaigns-not-playable | B101: Priorité du suivi | E101: PrioritesV158 | F101: Finir les corpus et campagnes des opérations déjà accessibles | G101: 21 accès V131 conservés ; 20 adaptations partielles / une effective | H101: Ces consultations précisent la provenance et les identités seulement ; le statut du chantier V158 reste inchangé. | I101: Le Cocon Noir vise résine, coupe et libération dédiées. Cela ne clôt pas extended-survivor-campaign et ne change pas les 20 statuts partial / un effective. | L101: 0 | M101: 0

Sheet 18_ChantiersV160
A1: Tantalus Frontier — V162
A2: 18_ChantiersV160
A3: Prépublication : implémentation et validation du commit restent distinctes.
A5: Chantier_ID | B5: Origine | C5: Chantier | D5: Périmètre livré en source | E5: Modules | F5: Vérifications prévues | G5: État technique prépublication | H5: Références | I5: Limites 1:1 | J5: Recette de la source prépublication | K5: Priorités liées | L5: Clôture artistique | M5: Approbation 1:1
A6: C160-PLAYER | B6: Demande utilisateur explicite V160 | C6: Corps du joueur | D6: Les pieds, le bassin, la ceinture, le thorax et les épaules de l’arme partagent le même repère de support au lieu de dissocier le haut et le bas du corps. La tête, le casque et le masque utilisent une attache réduite commune ; les hanches projetées sont resserrées. Les longueurs de cuisse/tibia restent rigides, les appuis plantés sont conservés et la cadence suit la distance réelle en marche et jogging. Les raccords de poses, d’échelle, de conduit et de chargement partiel conservent les supports natifs. La poche de recharge suit le tissu de la cuisse éloignée, y compris pendant les poses et le secours de chargement natif, au lieu de rester suspendue à un point vide. Lors d’un chargement incomplet, les sept pièces de jambes disponibles restent procédurales ; si leurs images manquent aussi, les vraies frames natives 4–7 suivent la phase de marche avec leurs propres ancres de semelle. Sur échelle, la posture entière s’écarte du montant pour que la main éloignée reste sur le vrai barreau dans l’enveloppe du coude, sans déplacer les barreaux ni changer les longueurs des membres. Pour le contact mural Jeri, l’identifiant et la face de la surface physique choisissent une posture de prise distincte de l’échelle centrée ; les mains et les pieds plantés visent la vraie face sans projection hors portée, et le plafond garde sa présentation propre. Au Port Méridien, même sous le wrapper spatial de production, le rig conserve les métadonnées du montage natif : pas de 24 pixels et premier barreau à 8 pixels sous le haut de l’échelle, au lieu du montage spatial du vaisseau à 22/11. Les contacts restent à l’intérieur des traverses peintes sans lire les pixels en direct ni déplacer le décor. | E6: src/player-human-proportions-v160.js ; src/player-body-rig-v125.js ; src/player-locomotion-rig-v129.js ; src/player-modular-rig-v126.js ; src/player-action-rig-v127.js ; src/player-transit-rig-v128.js ; src/player-gait-v133.js ; src/hive-missions-v131.js ; src/player-appearance-hub-v126.js | F6: scripts/verify-player-human-coherence-v160.mjs ; scripts/verify-player-body-alignment-v142.mjs ; scripts/verify-jeri-surface-motion-v135.mjs ; scripts/verify-player-climb-contacts-v139.mjs ; scripts/verify-human-gait-v133.mjs ; scripts/verify-human-motion-v136.mjs ; scripts/verify-player-appearance-runtime-v126.mjs | G6: Implémentation source ; recette exacte en attente | H6: V160-REF-006 ; V160-REF-007 ; V160-REF-008 ; V160-REF-009 ; V160-REF-010 | I6: Correction procédurale de dessins natifs conservés ; enveloppe de conception et mesures de pixels, pas calibration anatomique universelle. Le relevé CMU générique ne retargete aucun personnage de franchise. La collision native reste 42 × 92 unités ; les variantes finales des bras et les comparaisons visuelles avant/après attendent la recette du commit final. Le contact Jeri adapte le rig existant ; il ne fournit aucun nouvel art synthétique dédié ni animation de franchise certifiée. | J6: À vérifier sur le commit final | K6: costume-art ; excel-identity-and-motion | L6: 0 | M6: 0
A7: C160-TRACKER | B7: Demande utilisateur explicite V160 | C7: Détecteur de mouvement | D7: Q active la capacité native de détection à 900 unités du jeu : contacts de positions réellement mobiles dans le même repère/pont, balayage, échos datés et expiration. L’écran en coupe 2D ne révèle ni camp, espèce ou boss ; alliés, ennemis et conduits projetés ne sont suivis que sur mouvement mesuré. Bip et bruit tactique local suivent le temps actif après activation ; pauses, générations et changements de repère ne créent pas de dette de mouvement. Sur écran étroit, le boîtier compact se place d’après le corps et la caméra et affiche une portée relative sans attribuer des mètres aux unités du jeu. À bord, Q et le bouton natif du détecteur partagent la même activation, y compris au clavier focalisé et au clic assistif. Le déverrouillage audio commence dans le geste ; seule une reprise audio audible et suspendue retarde la consultation, puis l’identité du joueur, du propriétaire, de la génération, du repère et de l’impulsion est revérifiée. Un son muet, absent ou refusé laisse le gameplay disponible ; une demande devenue obsolète ne déclenche aucun scan tardif. Dans une mission de ruche active, les castes physiques du registre natif hiveActorsV131 participent au même échantillonnage de déplacement, sans distinction de loyauté ou de recrutement. Leurs échos restent anonymes et suivent les mêmes règles de vie, de scène et de disparition. | E7: src/motion-tracker-v160.js ; src/motion-tracker-display-v160.js ; src/game-v51-runtime.js ; src/game-production-base.js ; src/game-v52-level-runtime.js | F7: scripts/verify-motion-tracker-v160.mjs | G7: Implémentation source ; recette exacte en attente | H7: V160-REF-001 ; V160-REF-002 ; V160-REF-003 | I7: Adaptation inspirée du manuel officiel Alien: Isolation, distincte du modèle M314 du film. Pas de portée métrique canonique, d’identification IFF ou de copie 1:1 de son écran. Consultation native de 0,7 seconde puis projection HUD de cinq secondes ; aucun appareil tenu en continu n’est déclaré. Seuls les corps admis sont observés, pas les machines ou tous les accessoires mobiles. La dotation Q native reste distincte d’un consommable personnel. | J7: À vérifier sur le commit final | K7: excel-identity-and-motion | L7: 0 | M7: 0
A8: C160-WEAPONS | B8: Demande utilisateur explicite V160 | C8: Prise des armes et origine du tir | D8: Le solveur maintient les mains dans une enveloppe de conception réalisable, avec des zones de poignée, avant-main et port de service qui évitent la singularité près de l’épaule, et une portée d’épaule mesurée depuis le vrai torse. Le corps final V129 est résolu avant le canon et l’origine du tir. Lors d’un obstacle réel, la rétraction recalcule l’arme rigide et les mains sans déplacer la poche du corps pendant la recharge. Un aperçu pur de la pose après déclenchement, blessure et recul prévoit le vrai cadrage avant de dépenser une ressource ou de lancer un cycle. La projection du curseur peut être consultée sans mutation ; les gardes de tir et de commit refusent les cycles obstrués avant leur consommation. Le guide d’obstruction suit la garde physique courante : un ancien flag de pose ne bloque plus un canon réellement dégagé après un peek, et un vrai contact au mur conserve le refus avant ressources. Pour les tirs différés de charge ou de rafale, l’aperçu conserve l’orientation explicitement fournie ; si la visée stockée ne contient que x/y, son sens horizontal détermine le côté du corps, avec repli sur l’orientation de l’acteur pour une visée verticale. L’aperçu ne modifie pas cette visée. | E8: src/player-arm-constraints-v160.js ; src/held-weapon-renderer-v125.js ; src/player-weapon-runtime-v125.js ; src/player-appearance-runtime-v126.js ; src/mission-input-v77.js ; src/weapon-actions-v131.js | F8: scripts/verify-held-weapon-v125.mjs ; scripts/verify-player-weapon-rig-v125.mjs ; scripts/verify-weapon-actions-v131.mjs ; scripts/verify-player-runtime-v124.mjs ; scripts/verify-audit-v143.mjs ; scripts/verify-destructible-scenery-v130.mjs ; scripts/verify-forge-mission-v141.mjs ; scripts/verify-placeables-extension-v132.mjs | G8: Implémentation source ; recette exacte en attente | H8: V160-REF-004 ; V160-REF-007 | I8: Les 5°–145° du coude et −90°–150° du bras supérieur sont des enveloppes de conception projetées, pas des mesures biomécaniques ni une chorégraphie canonique. Dessins natifs conservés ; les comparaisons visuelles du corps final, de la branche de coude retenue et du retrait au mur attendent la recette exacte. | J8: À vérifier sur le commit final | K8: excel-identity-and-motion | L8: 0 | M8: 0
A9: C160-CAMPAIGN | B9: Demande utilisateur explicite V160 | C9: Continuité narrative Tantalus | D9: « Le dernier relais » approfondit QZ-18/Lethe dans l’opération special-archive-relay : cinq phases dialoguées avec portraits natifs, avec l’incident natif lorsqu’il est présent, choix de préparation technique ou de prévention à bord, six pièces persistantes et retour rattaché au même identifiant d’opération. Les retombées de recherche ou de moral exigent extraction native et dossier complet ; lecture/relecture ne récompensent jamais, et les blessures/échecs restent réels. Le déploiement emploie le même renderer QZ-18 que la mission ; les props réutilisent cinq atlas admis, au contact des vraies ancres, en 2D intégrale sans ajouter de collision. Les contrôles de sauvegarde en mission et de retour après extraction utilisent les handlers natifs ; le retour est libellé « RETOUR À BORD ». Le dernier compte rendu QZ-18 est conservé avec son dossier, accessible après une autre opération ; ce retour compact et borné garde son identifiant, son résultat, son protocole et son reçu de lecture/paiement. Il est affiché uniquement dans le plan QZ-18 ; le paiement lit seulement le résultat natif courant, jamais le retour archivé. Les insertions ordinaires retrouvent leurs interactions contextuelles et le cadrage des illustrations suit la progression persistée de la phase, sans redémarrer une animation à chaque rendu. Après normalisation native de la sauvegarde, les six lectures mettent à jour le bilan courant et son archive durable ensemble. Les dates proviennent seulement du retour validé de cette même opération, ou du dossier natif correspondant pour une ancienne victoire ; aucune date courante ni récompense supplémentaire n’est créée. Après reconstruction du plan, la question activée retrouve le focus clavier sans déplacement de page, y compris en relecture. | E9: src/campaign-story-v160.js ; src/campaign-story-ui-v160.js ; src/mission-insertion-ui-v62.js ; src/campaign-consequences.js ; src/archive-relay-presentation-v160.js ; src/archive-relay-runtime-v122.js ; mission-insertion-v62.css ; src/archive-relay-state-v122.js | F9: scripts/verify-campaign-story-v160.mjs ; scripts/verify-archive-relay-presentation-v160.mjs | G9: Implémentation source ; recette exacte en attente | H9: V160-REF-005 ; V160-REF-006 ; V160-REF-009 | I9: Intrigue Tantalus originale, sans reconstruction canonique Aliens ni conclusion sur une responsabilité personnelle. Les images de préparation du vaisseau restent illustratives ; seul le déploiement reprend la scène jouable. Ce parcours borné ne termine pas les corpus des vingt autres opérations. Comparaisons natives, reprise et résultats du commit final restent à vérifier. | J9: À vérifier sur le commit final | K9: campaigns-not-playable | L9: 0 | M9: 0

Sheet 19_ReferencesV160
A1: Tantalus Frontier — V162
A2: 19_ReferencesV160
A3: Prépublication : implémentation et validation du commit restent distinctes.
A5: Référence_ID | B5: Chantiers | C5: Type | D5: Œuvre / objet | E5: URL / source | F5: SHA256 observé | G5: Édition / localisation | H5: Portée observée | I5: Ne prouve pas | J5: État de récupération | K5: Date du constat | L5: Clôture artistique | M5: Approbation 1:1
A6: V160-REF-001 | B6: C160-TRACKER | C6: official-manual-text | D6: Alien: Isolation — The Collection | E6: https://www.feralinteractive.com/en/manuals/alienisolation/latest/steam/ | F6: b34ad1fbd9b69888fea05ee886fdf95278ce8018654c79c06ea0b5e06b79cd22 | G6: Official Feral Steam manual, latest URL; exact gameplay build unknown | H6: Movement-only contacts; stationary hostiles do not appear. ; Forward cone with flashing dots, side/rear quarter sectors, nearest movement distance, objective direction marker. ; Audible tracker beeps can reveal the user location. | I6: M314 Aliens-film identity or exact display. ; Exact scan range in metres, update rate, angular cone degrees or beep timing. ; IFF enemy/friend/species identification or all-deck omniscience. | J6: Consultation historique ou locale ; illustration nouvelle explicitement identifiée | K6: 2026-10-20T09:30:51.028624+00:00 | L6: 0 | M6: 0
A7: V160-REF-002 | B7: C160-TRACKER | C7: official-manual-illustration | D7: Alien: Isolation — The Collection | E7: https://www.feralinteractive.com/en/manuals/alienisolation/latest/steam/motion_tracker.jpg | F7: ac5ef11291d013636ee8bac24b110197eea155f7cda732ff3bfccfd348f57b07 | G7: Official Feral manual illustration; exact gameplay build unknown | H7: Green display with forward fan sector, arc markings and a luminous unclassified point. ; A lower-left distance number is visible; the screenshot reads 0.59 without establishing a world-unit conversion. ; Side indicators and a left edge rectangular marker are visible. | I7: M314 Aliens-film model, matching physical casing, source unit scale or an orthographic display projection. ; Actual motion timing or beep cadence from a still image. | J7: Consultation historique ou locale ; illustration nouvelle explicitement identifiée | K7: 2026-10-20T09:30:51.028624+00:00 | L7: 0 | M7: 0
A8: V160-REF-003 | B8: C160-TRACKER | C8: unretrieved-candidate | D8: M314 Motion Tracker — article candidate | E8: https://avp.fandom.com/wiki/M314_Motion_Tracker | F8: Aucun contenu récupéré | G8: Édition exacte non établie | I8: The article contents, exact URL identity, M314 display, movement rules or range. | J8: CONTENT_NOT_RETRIEVED_SINGLE_ATTEMPT_NO_RETRY | K8: 2026-10-20T09:30:51.028624+00:00 | L8: 0 | M8: 0
A9: V160-REF-004 | B9: C160-WEAPONS | C9: official-labelled-weapons-image | D9: Aliens: Fireteam Elite — Pathogen | E9: https://www.aliensfireteamelite.com/images/uploads/7c1e86e6cde1368364bb3f0cdbeed260.jpg | F9: 98a64bac9cbd09b69e9137b4c1a22b46e9e58d215b78e93e6cf95c579095912d | G9: Édition exacte non établie | H9: Labelled side silhouettes of EDS-93 Zadak Plasma Discharger, Thunderbolt Mk.2 Autocannon, LEM STG24 Storm Rifle and U1A2 GL Conversion. ; Visible grips, stocks, support handles and barrel axes of those four models only. | I9: M41A, M4A3 or other unpictured weapon geometry. ; Human hand placement, shouldering, recoil, reload or per-frame timings. ; Absolute physical dimensions from the montage. | J9: Consultation historique ou locale ; illustration nouvelle explicitement identifiée | K9: 2026-10-20T09:30:51.028624+00:00 | L9: 0 | M9: 0
A10: V160-REF-005 | B10: C160-CAMPAIGN | C10: official-film-synopsis | D10: Aliens (1986) | E10: https://www.20thcenturystudios.com/movies/aliens | F10: 29ac5109cfbdb1fcf53b9acb7e7a41e03a91ba6a2415ad51b5732be2c927c581 | G10: Extracted text line 23 synopsis; no film frames recovered | H10: Ripley returns from hypersleep after 57 years; lost contact with colonists leads to a military expedition. | I10: Tantalus, Echo-9, Mire-9 or the project original storyline. ; Cinematic shot timing, blocking, camera interpolation, gestures or dialogue exactness. | J10: Consultation historique ou locale ; illustration nouvelle explicitement identifiée | K10: 2026-10-20T09:30:51.028624+00:00 | L10: 0 | M10: 0
A11: V160-REF-006 | B11: C160-CAMPAIGN ; C160-PLAYER | C11: official-promotional-video-limited-framing | D11: Aliens: Fireteam Elite — Pathogen | E11: https://www.aliensfireteamelite.com/assets/html5/loop_desktop.mp4 | F11: 45e805ec67b0be20fe195d53efbdb246734b7f6746f0bef89f9c756adc346449 | G11: Pathogen visible on the closing title card; actual game build unknown | H11: The official montage advertises Pathogen; one environment establishing shot is identified at 1.001 s. | I11: A complete unobstructed human gait or arm cycle. ; Actual gameplay speed, exact build, skeletal proportions or inter-shot timing in the game. ; A canonical Tantalus scene. | J11: Consultation historique ou locale ; illustration nouvelle explicitement identifiée | K11: 2026-10-20T09:30:51.028624+00:00 | L11: 0 | M11: 0
A12: V160-REF-007 | B12: C160-PLAYER ; C160-WEAPONS | C12: existing-native-game-art-not-external-evidence | D12: Echo-9 modular colonial artwork | E12: Art natif du projet ou source absente | F12: assets/openai/sprites/player/colonial-v129/uscm-legs-v129.png:862d7afa275ee54d78e031d68ed461255804b3b5ad4d7534ba8fa2018a99165f ; assets/openai/sprites/player/colonial-v129/uscm-torso-right-v129.png:6be09c3d5ef197b0e1d343c530ec70a2eb13b03c1d2c7ca620c96f8dc7218cc5 ; assets/openai/sprites/tools/m314-motion-tracker-use-sheet.png:021536b998dbae4c7e6a17e4e65d3ad26b30877fcb59288a9f80d5b2041c623a | G12: Project baseline 4fc9da8, generated adapted sprite parts | H12: The native leg part contains pelvis, femur, shin and boot sprites with individual attachment openings. ; Native torso armour and tracker artwork can be used as the project visual style baseline. | I12: Film-accurate uniform details, true anatomical joint locations or movie tracker identity. ; A generated atlas is not an external canon source. | J12: Consultation historique ou locale ; illustration nouvelle explicitement identifiée | K12: 2026-10-20T09:30:51.028624+00:00 | L12: 0 | M12: 0
A13: V160-REF-008 | B13: C160-PLAYER | C13: missing-biomechanics-reference | D13: Human lower-limb biomechanics and body proportions | E13: Art natif du projet ou source absente | F13: Aucun contenu récupéré | G13: Édition exacte non établie | I13: Any exact universal knee/hip degree limit, body/head ratio, walking stride or duty factor. | J13: NO_AUTHORITATIVE_SOURCE_RETRIEVED | K13: 2026-10-20T09:30:51.028624+00:00 | L13: 0 | M13: 0
A14: V160-REF-009 | B14: C160-PLAYER ; C160-CAMPAIGN | C14: missing-requested-game-reference | D14: Terminator 2D: NO FATE | E14: Art natif du projet ou source absente | F14: Aucun contenu récupéré | G14: Édition exacte non établie | I14: A matching animation cycle, directional aiming implementation, room perspective or cinematics. | J14: NO_EXACT_LOCAL_SOURCE_OR_TIME_CODE_FOUND | K14: 2026-10-20T09:30:51.028624+00:00 | L14: 0 | M14: 0
A15: V160-REF-010 | B15: C160-PLAYER | C15: generic-human-motion-capture-reference | D15: CMU Graphics Lab Motion Capture Database — subject 02, trial 01, walk | E15: https://raw.githubusercontent.com/una-dinosauria/cmu-mocap/09a07f54f3bbb58797325f009282d0b2048a2871/data/002/02_01.bvh | F15: cf56db43157acc3d200b3d4215523f54d354a8926bea67e1f6c8031bd335ba7e | G15: Bruce Hahne MotionBuilder-friendly BVH 2010 release; T-pose estimated and prepended | H15: One identified generic human walk is available as a converted CMU BVH with 343 motion frames after excluding the synthetic added T-pose. ; The declared hierarchy and samples support exploratory geometric knee/segment comparison, using estimated scale and side projection only. ; The mirror conversion README rights statement was actually read; the primary CMU terms were not independently fetched. | I15: One walk capture by one performer, not universal joint limits or a canonical franchise animation. ; READMEFIRST explicitly warns CMU joint calibration/T-pose are guessed and source motion may contain impossible head angles/noise. ; Frame 0 is synthetic added T-pose; excluded from motion extrema. ; Knee flexion measured from 3D segment geometry; hip-like value uses world vertical/travel plane, not calibrated anatomical pelvis joint angle. ; Source game speed, phase, mapping near/far vs left/right differ; no 1:1 certification or direct target degree constraint. ; Source units, subject anthropometry and marker calibration not established. ; This source does not certify an Aliens, Terminator or other franchise animation. ; Finger/thumb motion is not captured according to the README; cannot validate weapon grip animation. ; No BVH, raw capture, PNG or private trace is proposed for the public repository. | J15: GENERIC_MOCAP_GEOMETRY_RETRIEVED_AND_ANALYSED | K15: 2026-10-20T09:34:03.191074+00:00 | L15: 0 | M15: 0

Sheet 20_ComparaisonsV160
A1: Tantalus Frontier — V162
A2: 20_ComparaisonsV160
A3: Prépublication : implémentation et validation du commit restent distinctes.
A5: Protocole_ID | B5: Chantier | C5: Paires à comparer | D5: Mesures | E5: Critères / limites | F5: État prévu de recette | G5: Approbation 1:1
A6: C160-PLAYER-VISUAL | B6: C160-PLAYER | C6: Neutral left/right next to the same human NPC and floor. ; At least one full slow walking cycle left/right, running cycle, brake and restart. ; Crouch idle/move, jump ascent/apex/landing, ladder step and vent entry/exit. ; Same camera zoom, viewport, outfit, neutral pose and known Save-picker fixture before/after. | D6: Silhouette alpha height/width and skull/waist/hip/floor landmarks. ; Distance between registered belt and pelvis centres; same single anatomical frame in both facings. ; Femur/shank world length constant across all poses; triangle reach remains feasible. ; Support-foot drift, knee bending direction, pelvis/torso continuity and clearance during swing. ; Frame-to-frame displacement/angle continuity, plus pause/read-only draw idempotence. | E6: No detached waist, reversed knee, below-floor sole or visibly rescaled leg across postures. ; Numeric constraints are engineering plausibility checks; external anatomical 1:1 remains unapproved. | F6: À vérifier sur le commit final ; protocole distinct des contrôles exécutés | G6: 0
A7: C160-TRACKER-VISUAL | B7: C160-TRACKER | C7: Empty scan, one moving front contact, same actor stopped, rear/side movement and multiple actors. ; Left/right facing, changing deck/room, active cinematic/pause and resume. ; Tracker absent/unselected and no hidden actor ID/species labels. | D7: Screen centre and direction map to the player pose in the active coordinate chart. ; Range and distance use explicitly named game units; radar radius boundary matches the actual filter. ; Contacts require measured actor movement; user movement alone cannot animate a stationary entity. ; Scan refresh and beep schedule advance by simulation time and hold during pause. | E7: UI compared to official Isolation illustration as an attributed adaptation, not a faithful M314 recreation. ; No wall-occlusion or deck omniscience claimed as movie canon. | F7: À vérifier sur le commit final ; protocole distinct des contrôles exécutés | G7: 0
A8: C160-WEAPONS-VISUAL | B8: C160-WEAPONS | C8: Primary/sidearm/heavy or launcher in both facings. ; Eight aim directions, muzzle shot onset, recoil recovery and reload stages. ; Crouching, moving, aiming backwards and tracker/tool swap. | D8: Grip/hand and stock/shoulder anchor residuals after their actual shared matrices. ; Rendered barrel axis intersects actual projectile origin/velocity, with no backwards muzzle flash. ; No arm IK beyond reachable length; bone lengths invariant after tool/weapon swaps. ; Local silhouette ratios compared only with an identified corresponding model source. | E8: No firearm-size claim from mixed-source image grids. ; Unpictured M41A or other models retain source gaps. | F8: À vérifier sur le commit final ; protocole distinct des contrôles exécutés | G8: 0
A9: C160-CAMPAIGN-VISUAL | B9: C160-CAMPAIGN | C9: Opening shot→interactive choice→mission consequence→return/debrief. ; Same sequence after Save reload, reduced-motion, skip and failure. | D9: Scene geography and character blocking agree with the following playable room. ; Choice text, actual persisted consequence and return dialogue refer to the same event. ; Skip/replay cannot duplicate rewards or skip required gameplay state. ; Camera/text fit same viewport and remain usable in small-screen layouts. | E9: Original Tantalus story is labelled as project fiction; film synopsis is context only. ; Promotional framing is inspiration, not proof of exact cinematic duration or a canonical scene. | F9: À vérifier sur le commit final ; protocole distinct des contrôles exécutés | G9: 0

Sheet 21_ChantiersV161
A1: Tantalus Frontier — V162
A2: 21_ChantiersV161
A3: Prépublication : implémentation et validation du commit restent distinctes.
A5: Chantier_ID | B5: Chantier | C5: Priorités liées | D5: Périmètre implémenté | E5: Modules | F5: Vérifications prévues | G5: Recette de la source | H5: Limites restantes | I5: Clôture artistique | J5: Approbation 1:1
A6: C161-FORGE | B6: Progression de campagne locale Forge | C6: forge-test-persistence ; forge-narrative-events | D6: Une campagne locale ordonnée conserve les documents figés de deux à seize projets Mission/Vaisseau. Seule la réussite native de l’étape exacte ouvre la suivante ; les objectifs et choix narratifs sont conservés dans le reçu. Le prochain départ reste explicite, la progression des étapes terminées survit au rechargement et les modifications ultérieures des projets source ne réécrivent pas leurs copies. Les écritures locales détectent les conflits entre onglets et préservent les données corrompues sans les écraser. | E6: src/forge-campaign-v161.js ; src/forge-campaign-ui-v161.js ; src/app.js ; src/forge-editor-v130.css | F6: scripts/verify-forge-campaign-v161.mjs | G6: À vérifier sur le commit final | H6: Un emplacement local de 8 Mio ; une étape inachevée redémarre. Les checkpoints restent distincts et détachent la propriété de campagne. Aucun transport d’équipement ou d’inventaire entre étapes, branchement, cloud ou script libre livré ; aucun corpus complet de campagne ou 1:1 déclaré. | I6: 0 | J6: 0
A7: C161-CAMPAIGN | B7: Continuité originale du convoi APC | C7: campaigns-not-playable | D7: Le départ APC développe cinq phases originales Tantalus avec un choix facultatif de lecture du blindage ou du parcours, conservé sans bonus économique. Sept jalons natifs alimentent la radio et le HUD APC est regroupé. Trois questions de retour lisent seulement le résultat terminal et le checkpoint de la même opération native ; les lectures bornées dans insertionState survivent à la sauvegarde normalisée, sans rejouer de paiement. | E7: src/campaign-convoy-story-v161.js ; src/campaign-convoy-story-ui-v161.js ; src/mission-insertion-ui-v62.js ; src/apc-convoy-runtime-v121.js ; src/apc-course-v131.js ; src/app.js | F7: scripts/verify-campaign-convoy-story-v161.mjs | G7: À vérifier sur le commit final | H7: Un seul compte rendu lié à lastOperation ; une opération ultérieure peut le remplacer. Aucun archivage durable global, campagne complète, canon 1:1, voix ou dessin nouveau. Une ancienne reprise sans insertionState rejoint directement le jeu natif et conserve un débrief local en lecture seule. Aucun bonus supplémentaire. | I7: 0 | J7: 0
A8: C161-CREW | B8: Circuits de service réacteur et cuisine | C8: annex-crew-coverage | D8: Deux circuits natifs relient Idris entre le réacteur et la salle des machines du pont 3, et Leila entre le mess et la cuisine du pont 1. Les mêmes acteurs de 44 × 92 unités marchent sur le sol 624 jusqu’aux vraies portes appariées ; leur changement de repère se produit uniquement derrière les vantaux opaques entièrement fermés. Les deux faces du cadre cuisine sont agrandies uniformément pour contenir la silhouette native ; les plaques suivent le cadre réel avec dix pixels de dégagement. Le retour aux routines natives respecte la composition des trois propriétaires de circuit pour conserver les autres acteurs à terre ou en récupération médicale. L’état borné conserve les phases à la reprise et réagit aux interruptions, aux passages occupés et aux dialogues natifs. | E8: src/npc-service-routes-v161.js ; src/save.js ; src/app.js ; src/hub-destination-signage-runtime-v138.js ; src/npc-annex-circulation-v159.js | F8: scripts/verify-npc-service-routes-v161.mjs | G8: À vérifier sur le commit final | H8: Les deux routes sont des circuits parent/annexe bornés : aucun ascenseur, trajet physique entre ponts, nouveau dessin ou sprite de dos. Le retour aux routines natives après le service est signalé séparément et son déplacement ultérieur n’est pas observé ; les dix-neuf annexes ne sont pas couvertes par ce lot. | I8: 0 | J8: 0

Sheet 22_ChantiersV162
A1: Tantalus Frontier — V162
A2: 22_ChantiersV162
A3: Prépublication : implémentation et validation du commit restent distinctes.
A5: Chantier_ID | B5: Chantier | C5: Priorités liées | D5: Périmètre source ou recette | E5: Modules | F5: Vérifications prévues | G5: Recette de la source | H5: Limites restantes | I5: Clôture artistique | J5: Approbation 1:1
A6: C162-HARPOON | B6: Harpoon : préservation du tir à la fermeture | C6: legacy-backlog-triage | D6: La sauvegarde du checkpoint de mission est capturée avant le nettoyage de fermeture du moteur. Dans le défaut reproduit sur le Harpoon natif 024, le moteur supprimait les projectiles et récupérables avant leur capture ; le nouvel ordre préserve le vrai état avant stop, sans modifier les modules d’armes. Le pilote natif contrôle achat, équipement, tir, impact, récupération et reprise des quatre variantes 024/064/104/144 dans QZ-18. | E6: src/app.js | F6: scripts/verify-harpoon-unload-v162.mjs ; scripts/verify-weapon-actions-v131.mjs ; scripts/qa-harpoon-native-v162.py | G6: À vérifier sur le commit final | H6: Le défaut de fermeture et le vieux blocage d’achat V61 sont deux constats distincts. Aucun nouveau module d’arme, dessin ou source canonique. La recette des quatre variantes sur le commit final reste à exécuter ; les parcours initiaux ne sont pas transférés comme résultats finaux. | I6: 0 | J6: 0
A7: C162-AUDIO | B7: Cycle audio natif et banques | C7: legacy-backlog-triage | D7: Le correctif refuse les effets décodés et la synthèse lorsque le volume maître est nul, afin qu’une réactivation rapide ne révèle pas leur fin ou une alarme différée. Les nouvelles régressions exercent séparément les mécanismes hérités : annulation de la seconde note d’une alarme à la coupure des effets et rejet des transferts de musique devenus obsolètes. Les huit banques et les reprises natives disposent d’un pilote distinct, sans nouveau média. | E7: src/audio.js | F7: scripts/verify-audio-lifecycle-v162.mjs ; scripts/qa-audio-native-v162.py | G7: À vérifier sur le commit final | H7: Aucune nouvelle musique, voix, banque originale ou source de franchise. Le pilote Chromium headless active réellement un autre onglet et minimise la fenêtre, mais document.hidden n’y est pas observé : aucun parcours de scène masquée réussi n’est certifié. Un contrôle automatisé ne certifie pas le rendu sur haut-parleurs ou appareils physiques ; recette exacte à exécuter. | I7: 0 | J7: 0
A8: C162-CREW | B8: Circuit médical vers la morgue | C8: annex-crew-coverage | D8: Noor Okafor relie l’infirmerie à la morgue du pont 1 pour son service médico-légal. Le circuit reprend le même acteur de 44 × 92 unités, le sol 624, les sockets natifs et la fermeture opaque des portes. Le créneau de soins animaliers 09 h–10 h 30 est préservé par un retour réel à l’infirmerie puis une délégation native signalée comme non observée. Le pilote calcule l’arrivée de retour depuis le vrai cadre de porte, relâche les touches et observe le freinage avant de vérifier l’occupation durant au moins 0,15 seconde simulée. L’attente mesure la progression physique avec des bornes distinctes de simulation, de temps mural et de blocage ; cette adaptation de recette ne change pas le jeu. | E8: src/npc-medical-route-v162.js ; src/npc-service-routes-v161.js | F8: scripts/verify-npc-medical-route-v162.mjs ; scripts/qa-npc-medical-route-v162.py | G8: À vérifier sur le commit final | H8: Un circuit parent/annexe borné. Aucun ascenseur, déplacement physique entre ponts, nouveau dessin ou cycle de dos. Les soins, missions et autres priorités restent natifs ; le trajet après délégation n’est pas prouvé par ce lot. | I8: 0 | J8: 0
A9: C162-APC | B9: Archive bornée des retours APC | C9: campaigns-not-playable | D9: Une archive compacte conserve au plus huit résultats APC natifs distincts, avec leurs relevés de distance, barrages, reine, blindage réel, protocole et trois lectures validées. L’admission exige le même identifiant d’opération, campagne, monde, numéro de résolution, déploiement et état terminal ; le succès exige son reçu complet, et l’échec ne conserve que le checkpoint partiel réel clairement désigné. L’identité V84 de l’opérateur est figée lorsqu’elle est valide ; les anciens retours peuvent rester anonymes. La consultation est en lecture seule et ne verse aucune récompense. | E9: src/campaign-convoy-history-v162.js ; src/campaign-convoy-history-ui-v162.js ; campaign-convoy-history-v162.css | F9: scripts/verify-campaign-convoy-history-v162.mjs ; scripts/qa-campaign-convoy-history-v162.py | G9: À vérifier sur le commit final | H9: Journal de huit retours au plus, pas campagne étendue, enregistrement vidéo ou nouveau canon. Seuls les vrais résultats admissibles sont capturés ; aucun résultat absent n’est inventé et la lecture ne rejoue pas de paiement. | I9: 0 | J9: 0
